Workbook
Name IncomeCategories: 'Categories'!$A$3:$A$6
Name MainCategories: 'Categories'!$F$3:$F$12
Name Cat_Land_Legal: 'Categories'!$H$3:$H$9
Name Cat_Site_Development: 'Categories'!$I$3:$I$11
Name Cat_Utilities: 'Categories'!$J$3:$J$9
Name Cat_Landscaping: 'Categories'!$K$3:$K$7
Name Cat_Buildings_Amenities: 'Categories'!$L$3:$L$10
Name Cat_Labour_Contractors: 'Categories'!$M$3:$M$7
Name Cat_Materials: 'Categories'!$N$3:$N$11
Name Cat_Operations: 'Categories'!$O$3:$O$9
Name Cat_Marketing_Sales: 'Categories'!$P$3:$P$8
Name Cat_Miscellaneous: 'Categories'!$Q$3:$Q$7

Sheet Dashboard
A1: Site Expense Dashboard
A3: Current Cash Balance | C3: YTD Total Receipts | E3: YTD Total Payments | G3: Net Position (YTD)
A4: ='Dec2026'!B106 | C4: =SUM(B45:B56) | E4: =SUM(C45:C56) | G4: =C4-E4
A44: Month | B44: Receipts | C44: Payments | D44: Closing Balance | F44: Main Category | G44: Amount | I44: Income Category | J44: Amount | L44: Payment Mode | M44: Amount
A45: Jan2026 | B45: ='Jan2026'!B104 | C45: ='Jan2026'!B105 | D45: ='Jan2026'!B106 | F45: Land & Legal | G45: =SUMIFS(Jan2026!K3:K100,Jan2026!L3:L100,$F45)+SUMIFS(Feb2026!K3:K100,Feb2026!L3:L100,$F45)+SUMIFS(Mar2026!K3:K100,Mar2026!L3:L100,$F45)+SUMIFS(Apr2026!K3:K100,Apr2026!L3:L100,$F45)+SUMIFS(May2026!K3:K100,May2026!L3:L100,$F45)+SUMIFS(Jun2026!K3:K100,Jun2026!L3:L100,$F45)+SUMIFS(Jul2026!K3:K100,Jul2026!L3:L100,$F45)+SUMIFS(Aug2026!K3:K100,Aug2026!L3:L100,$F45)+SUMIFS(Sep2026!K3:K100,Sep2026!L3:L100,$F45)+SUMIFS(Oct2026!K3:K100,Oct2026!L3:L100,$F45)+SUMIFS(Nov2026!K3:K100,Nov2026!L3:L100,$F45)+SUMIFS(Dec2026!K3:K100,Dec2026!L3:L100,$F45) | I45: Investor Capital | J45: =SUMIFS(Jan2026!D3:D100,Jan2026!E3:E100,$I45)+SUMIFS(Feb2026!D3:D100,Feb2026!E3:E100,$I45)+SUMIFS(Mar2026!D3:D100,Mar2026!E3:E100,$I45)+SUMIFS(Apr2026!D3:D100,Apr2026!E3:E100,$I45)+SUMIFS(May2026!D3:D100,May2026!E3:E100,$I45)+SUMIFS(Jun2026!D3:D100,Jun2026!E3:E100,$I45)+SUMIFS(Jul2026!D3:D100,Jul2026!E3:E100,$I45)+SUMIFS(Aug2026!D3:D100,Aug2026!E3:E100,$I45)+SUMIFS(Sep2026!D3:D100,Sep2026!E3:E100,$I45)+SUMIFS(Oct2026!D3:D100,Oct2026!E3:E100,$I45)+SUMIFS(Nov2026!D3:D100,Nov2026!E3:E100,$I45)+SUMIFS(Dec2026!D3:D100,Dec2026!E3:E100,$I45) | L45: Bank | M45: =SUMIFS(Jan2026!D3:D100,Jan2026!F3:F100,$L45)+SUMIFS(Jan2026!K3:K100,Jan2026!N3:N100,$L45)+SUMIFS(Feb2026!D3:D100,Feb2026!F3:F100,$L45)+SUMIFS(Feb2026!K3:K100,Feb2026!N3:N100,$L45)+SUMIFS(Mar2026!D3:D100,Mar2026!F3:F100,$L45)+SUMIFS(Mar2026!K3:K100,Mar2026!N3:N100,$L45)+SUMIFS(Apr2026!D3:D100,Apr2026!F3:F100,$L45)+SUMIFS(Apr2026!K3:K100,Apr2026!N3:N100,$L45)+SUMIFS(May2026!D3:D100,May2026!F3:F100,$L45)+SUMIFS(May2026!K3:K100,May2026!N3:N100,$L45)+SUMIFS(Jun2026!D3:D100,Jun2026!F3:F100,$L45)+SUMIFS(Jun2026!K3:K100,Jun2026!N3:N100,$L45)+SUMIFS(Jul2026!D3:D100,Jul2026!F3:F100,$L45)+SUMIFS(Jul2026!K3:K100,Jul2026!N3:N100,$L45)+SUMIFS(Aug2026!D3:D100,Aug2026!F3:F100,$L45)+SUMIFS(Aug2026!K3:K100,Aug2026!N3:N100,$L45)+SUMIFS(Sep2026!D3:D100,Sep2026!F3:F100,$L45)+SUMIFS(Sep2026!K3:K100,Sep2026!N3:N100,$L45)+SUMIFS(Oct2026!D3:D100,Oct2026!F3:F100,$L45)+SUMIFS(Oct2026!K3:K100,Oct2026!N3:N100,$L45)+SUMIFS(Nov2026!D3:D100,Nov2026!F3:F100,$L45)+SUMIFS(Nov2026!K3:K100,Nov2026!N3:N100,$L45)+SUMIFS(Dec2026!D3:D100,Dec2026!F3:F100,$L45)+SUMIFS(Dec2026!K3:K100,Dec2026!N3:N100,$L45)
A46: Feb2026 | B46: ='Feb2026'!B104 | C46: ='Feb2026'!B105 | D46: ='Feb2026'!B106 | F46: Site Development | G46: =SUMIFS(Jan2026!K3:K100,Jan2026!L3:L100,$F46)+SUMIFS(Feb2026!K3:K100,Feb2026!L3:L100,$F46)+SUMIFS(Mar2026!K3:K100,Mar2026!L3:L100,$F46)+SUMIFS(Apr2026!K3:K100,Apr2026!L3:L100,$F46)+SUMIFS(May2026!K3:K100,May2026!L3:L100,$F46)+SUMIFS(Jun2026!K3:K100,Jun2026!L3:L100,$F46)+SUMIFS(Jul2026!K3:K100,Jul2026!L3:L100,$F46)+SUMIFS(Aug2026!K3:K100,Aug2026!L3:L100,$F46)+SUMIFS(Sep2026!K3:K100,Sep2026!L3:L100,$F46)+SUMIFS(Oct2026!K3:K100,Oct2026!L3:L100,$F46)+SUMIFS(Nov2026!K3:K100,Nov2026!L3:L100,$F46)+SUMIFS(Dec2026!K3:K100,Dec2026!L3:L100,$F46) | I46: Partner Contribution | J46: =SUMIFS(Jan2026!D3:D100,Jan2026!E3:E100,$I46)+SUMIFS(Feb2026!D3:D100,Feb2026!E3:E100,$I46)+SUMIFS(Mar2026!D3:D100,Mar2026!E3:E100,$I46)+SUMIFS(Apr2026!D3:D100,Apr2026!E3:E100,$I46)+SUMIFS(May2026!D3:D100,May2026!E3:E100,$I46)+SUMIFS(Jun2026!D3:D100,Jun2026!E3:E100,$I46)+SUMIFS(Jul2026!D3:D100,Jul2026!E3:E100,$I46)+SUMIFS(Aug2026!D3:D100,Aug2026!E3:E100,$I46)+SUMIFS(Sep2026!D3:D100,Sep2026!E3:E100,$I46)+SUMIFS(Oct2026!D3:D100,Oct2026!E3:E100,$I46)+SUMIFS(Nov2026!D3:D100,Nov2026!E3:E100,$I46)+SUMIFS(Dec2026!D3:D100,Dec2026!E3:E100,$I46) | L46: Cash | M46: =SUMIFS(Jan2026!D3:D100,Jan2026!F3:F100,$L46)+SUMIFS(Jan2026!K3:K100,Jan2026!N3:N100,$L46)+SUMIFS(Feb2026!D3:D100,Feb2026!F3:F100,$L46)+SUMIFS(Feb2026!K3:K100,Feb2026!N3:N100,$L46)+SUMIFS(Mar2026!D3:D100,Mar2026!F3:F100,$L46)+SUMIFS(Mar2026!K3:K100,Mar2026!N3:N100,$L46)+SUMIFS(Apr2026!D3:D100,Apr2026!F3:F100,$L46)+SUMIFS(Apr2026!K3:K100,Apr2026!N3:N100,$L46)+SUMIFS(May2026!D3:D100,May2026!F3:F100,$L46)+SUMIFS(May2026!K3:K100,May2026!N3:N100,$L46)+SUMIFS(Jun2026!D3:D100,Jun2026!F3:F100,$L46)+SUMIFS(Jun2026!K3:K100,Jun2026!N3:N100,$L46)+SUMIFS(Jul2026!D3:D100,Jul2026!F3:F100,$L46)+SUMIFS(Jul2026!K3:K100,Jul2026!N3:N100,$L46)+SUMIFS(Aug2026!D3:D100,Aug2026!F3:F100,$L46)+SUMIFS(Aug2026!K3:K100,Aug2026!N3:N100,$L46)+SUMIFS(Sep2026!D3:D100,Sep2026!F3:F100,$L46)+SUMIFS(Sep2026!K3:K100,Sep2026!N3:N100,$L46)+SUMIFS(Oct2026!D3:D100,Oct2026!F3:F100,$L46)+SUMIFS(Oct2026!K3:K100,Oct2026!N3:N100,$L46)+SUMIFS(Nov2026!D3:D100,Nov2026!F3:F100,$L46)+SUMIFS(Nov2026!K3:K100,Nov2026!N3:N100,$L46)+SUMIFS(Dec2026!D3:D100,Dec2026!F3:F100,$L46)+SUMIFS(Dec2026!K3:K100,Dec2026!N3:N100,$L46)
A47: Mar2026 | B47: ='Mar2026'!B104 | C47: ='Mar2026'!B105 | D47: ='Mar2026'!B106 | F47: Utilities | G47: =SUMIFS(Jan2026!K3:K100,Jan2026!L3:L100,$F47)+SUMIFS(Feb2026!K3:K100,Feb2026!L3:L100,$F47)+SUMIFS(Mar2026!K3:K100,Mar2026!L3:L100,$F47)+SUMIFS(Apr2026!K3:K100,Apr2026!L3:L100,$F47)+SUMIFS(May2026!K3:K100,May2026!L3:L100,$F47)+SUMIFS(Jun2026!K3:K100,Jun2026!L3:L100,$F47)+SUMIFS(Jul2026!K3:K100,Jul2026!L3:L100,$F47)+SUMIFS(Aug2026!K3:K100,Aug2026!L3:L100,$F47)+SUMIFS(Sep2026!K3:K100,Sep2026!L3:L100,$F47)+SUMIFS(Oct2026!K3:K100,Oct2026!L3:L100,$F47)+SUMIFS(Nov2026!K3:K100,Nov2026!L3:L100,$F47)+SUMIFS(Dec2026!K3:K100,Dec2026!L3:L100,$F47) | I47: Loan Received | J47: =SUMIFS(Jan2026!D3:D100,Jan2026!E3:E100,$I47)+SUMIFS(Feb2026!D3:D100,Feb2026!E3:E100,$I47)+SUMIFS(Mar2026!D3:D100,Mar2026!E3:E100,$I47)+SUMIFS(Apr2026!D3:D100,Apr2026!E3:E100,$I47)+SUMIFS(May2026!D3:D100,May2026!E3:E100,$I47)+SUMIFS(Jun2026!D3:D100,Jun2026!E3:E100,$I47)+SUMIFS(Jul2026!D3:D100,Jul2026!E3:E100,$I47)+SUMIFS(Aug2026!D3:D100,Aug2026!E3:E100,$I47)+SUMIFS(Sep2026!D3:D100,Sep2026!E3:E100,$I47)+SUMIFS(Oct2026!D3:D100,Oct2026!E3:E100,$I47)+SUMIFS(Nov2026!D3:D100,Nov2026!E3:E100,$I47)+SUMIFS(Dec2026!D3:D100,Dec2026!E3:E100,$I47)
A48: Apr2026 | B48: ='Apr2026'!B104 | C48: ='Apr2026'!B105 | D48: ='Apr2026'!B106 | F48: Landscaping | G48: =SUMIFS(Jan2026!K3:K100,Jan2026!L3:L100,$F48)+SUMIFS(Feb2026!K3:K100,Feb2026!L3:L100,$F48)+SUMIFS(Mar2026!K3:K100,Mar2026!L3:L100,$F48)+SUMIFS(Apr2026!K3:K100,Apr2026!L3:L100,$F48)+SUMIFS(May2026!K3:K100,May2026!L3:L100,$F48)+SUMIFS(Jun2026!K3:K100,Jun2026!L3:L100,$F48)+SUMIFS(Jul2026!K3:K100,Jul2026!L3:L100,$F48)+SUMIFS(Aug2026!K3:K100,Aug2026!L3:L100,$F48)+SUMIFS(Sep2026!K3:K100,Sep2026!L3:L100,$F48)+SUMIFS(Oct2026!K3:K100,Oct2026!L3:L100,$F48)+SUMIFS(Nov2026!K3:K100,Nov2026!L3:L100,$F48)+SUMIFS(Dec2026!K3:K100,Dec2026!L3:L100,$F48) | I48: Sales | J48: =SUMIFS(Jan2026!D3:D100,Jan2026!E3:E100,$I48)+SUMIFS(Feb2026!D3:D100,Feb2026!E3:E100,$I48)+SUMIFS(Mar2026!D3:D100,Mar2026!E3:E100,$I48)+SUMIFS(Apr2026!D3:D100,Apr2026!E3:E100,$I48)+SUMIFS(May2026!D3:D100,May2026!E3:E100,$I48)+SUMIFS(Jun2026!D3:D100,Jun2026!E3:E100,$I48)+SUMIFS(Jul2026!D3:D100,Jul2026!E3:E100,$I48)+SUMIFS(Aug2026!D3:D100,Aug2026!E3:E100,$I48)+SUMIFS(Sep2026!D3:D100,Sep2026!E3:E100,$I48)+SUMIFS(Oct2026!D3:D100,Oct2026!E3:E100,$I48)+SUMIFS(Nov2026!D3:D100,Nov2026!E3:E100,$I48)+SUMIFS(Dec2026!D3:D100,Dec2026!E3:E100,$I48)
A49: May2026 | B49: ='May2026'!B104 | C49: ='May2026'!B105 | D49: ='May2026'!B106 | F49: Buildings & Amenities | G49: =SUMIFS(Jan2026!K3:K100,Jan2026!L3:L100,$F49)+SUMIFS(Feb2026!K3:K100,Feb2026!L3:L100,$F49)+SUMIFS(Mar2026!K3:K100,Mar2026!L3:L100,$F49)+SUMIFS(Apr2026!K3:K100,Apr2026!L3:L100,$F49)+SUMIFS(May2026!K3:K100,May2026!L3:L100,$F49)+SUMIFS(Jun2026!K3:K100,Jun2026!L3:L100,$F49)+SUMIFS(Jul2026!K3:K100,Jul2026!L3:L100,$F49)+SUMIFS(Aug2026!K3:K100,Aug2026!L3:L100,$F49)+SUMIFS(Sep2026!K3:K100,Sep2026!L3:L100,$F49)+SUMIFS(Oct2026!K3:K100,Oct2026!L3:L100,$F49)+SUMIFS(Nov2026!K3:K100,Nov2026!L3:L100,$F49)+SUMIFS(Dec2026!K3:K100,Dec2026!L3:L100,$F49)
A50: Jun2026 | B50: ='Jun2026'!B104 | C50: ='Jun2026'!B105 | D50: ='Jun2026'!B106 | F50: Labour & Contractors | G50: =SUMIFS(Jan2026!K3:K100,Jan2026!L3:L100,$F50)+SUMIFS(Feb2026!K3:K100,Feb2026!L3:L100,$F50)+SUMIFS(Mar2026!K3:K100,Mar2026!L3:L100,$F50)+SUMIFS(Apr2026!K3:K100,Apr2026!L3:L100,$F50)+SUMIFS(May2026!K3:K100,May2026!L3:L100,$F50)+SUMIFS(Jun2026!K3:K100,Jun2026!L3:L100,$F50)+SUMIFS(Jul2026!K3:K100,Jul2026!L3:L100,$F50)+SUMIFS(Aug2026!K3:K100,Aug2026!L3:L100,$F50)+SUMIFS(Sep2026!K3:K100,Sep2026!L3:L100,$F50)+SUMIFS(Oct2026!K3:K100,Oct2026!L3:L100,$F50)+SUMIFS(Nov2026!K3:K100,Nov2026!L3:L100,$F50)+SUMIFS(Dec2026!K3:K100,Dec2026!L3:L100,$F50)
A51: Jul2026 | B51: ='Jul2026'!B104 | C51: ='Jul2026'!B105 | D51: ='Jul2026'!B106 | F51: Materials | G51: =SUMIFS(Jan2026!K3:K100,Jan2026!L3:L100,$F51)+SUMIFS(Feb2026!K3:K100,Feb2026!L3:L100,$F51)+SUMIFS(Mar2026!K3:K100,Mar2026!L3:L100,$F51)+SUMIFS(Apr2026!K3:K100,Apr2026!L3:L100,$F51)+SUMIFS(May2026!K3:K100,May2026!L3:L100,$F51)+SUMIFS(Jun2026!K3:K100,Jun2026!L3:L100,$F51)+SUMIFS(Jul2026!K3:K100,Jul2026!L3:L100,$F51)+SUMIFS(Aug2026!K3:K100,Aug2026!L3:L100,$F51)+SUMIFS(Sep2026!K3:K100,Sep2026!L3:L100,$F51)+SUMIFS(Oct2026!K3:K100,Oct2026!L3:L100,$F51)+SUMIFS(Nov2026!K3:K100,Nov2026!L3:L100,$F51)+SUMIFS(Dec2026!K3:K100,Dec2026!L3:L100,$F51)
A52: Aug2026 | B52: ='Aug2026'!B104 | C52: ='Aug2026'!B105 | D52: ='Aug2026'!B106 | F52: Operations | G52: =SUMIFS(Jan2026!K3:K100,Jan2026!L3:L100,$F52)+SUMIFS(Feb2026!K3:K100,Feb2026!L3:L100,$F52)+SUMIFS(Mar2026!K3:K100,Mar2026!L3:L100,$F52)+SUMIFS(Apr2026!K3:K100,Apr2026!L3:L100,$F52)+SUMIFS(May2026!K3:K100,May2026!L3:L100,$F52)+SUMIFS(Jun2026!K3:K100,Jun2026!L3:L100,$F52)+SUMIFS(Jul2026!K3:K100,Jul2026!L3:L100,$F52)+SUMIFS(Aug2026!K3:K100,Aug2026!L3:L100,$F52)+SUMIFS(Sep2026!K3:K100,Sep2026!L3:L100,$F52)+SUMIFS(Oct2026!K3:K100,Oct2026!L3:L100,$F52)+SUMIFS(Nov2026!K3:K100,Nov2026!L3:L100,$F52)+SUMIFS(Dec2026!K3:K100,Dec2026!L3:L100,$F52)
A53: Sep2026 | B53: ='Sep2026'!B104 | C53: ='Sep2026'!B105 | D53: ='Sep2026'!B106 | F53: Marketing & Sales | G53: =SUMIFS(Jan2026!K3:K100,Jan2026!L3:L100,$F53)+SUMIFS(Feb2026!K3:K100,Feb2026!L3:L100,$F53)+SUMIFS(Mar2026!K3:K100,Mar2026!L3:L100,$F53)+SUMIFS(Apr2026!K3:K100,Apr2026!L3:L100,$F53)+SUMIFS(May2026!K3:K100,May2026!L3:L100,$F53)+SUMIFS(Jun2026!K3:K100,Jun2026!L3:L100,$F53)+SUMIFS(Jul2026!K3:K100,Jul2026!L3:L100,$F53)+SUMIFS(Aug2026!K3:K100,Aug2026!L3:L100,$F53)+SUMIFS(Sep2026!K3:K100,Sep2026!L3:L100,$F53)+SUMIFS(Oct2026!K3:K100,Oct2026!L3:L100,$F53)+SUMIFS(Nov2026!K3:K100,Nov2026!L3:L100,$F53)+SUMIFS(Dec2026!K3:K100,Dec2026!L3:L100,$F53)
A54: Oct2026 | B54: ='Oct2026'!B104 | C54: ='Oct2026'!B105 | D54: ='Oct2026'!B106 | F54: Miscellaneous | G54: =SUMIFS(Jan2026!K3:K100,Jan2026!L3:L100,$F54)+SUMIFS(Feb2026!K3:K100,Feb2026!L3:L100,$F54)+SUMIFS(Mar2026!K3:K100,Mar2026!L3:L100,$F54)+SUMIFS(Apr2026!K3:K100,Apr2026!L3:L100,$F54)+SUMIFS(May2026!K3:K100,May2026!L3:L100,$F54)+SUMIFS(Jun2026!K3:K100,Jun2026!L3:L100,$F54)+SUMIFS(Jul2026!K3:K100,Jul2026!L3:L100,$F54)+SUMIFS(Aug2026!K3:K100,Aug2026!L3:L100,$F54)+SUMIFS(Sep2026!K3:K100,Sep2026!L3:L100,$F54)+SUMIFS(Oct2026!K3:K100,Oct2026!L3:L100,$F54)+SUMIFS(Nov2026!K3:K100,Nov2026!L3:L100,$F54)+SUMIFS(Dec2026!K3:K100,Dec2026!L3:L100,$F54)
A55: Nov2026 | B55: ='Nov2026'!B104 | C55: ='Nov2026'!B105 | D55: ='Nov2026'!B106
A56: Dec2026 | B56: ='Dec2026'!B104 | C56: ='Dec2026'!B105 | D56: ='Dec2026'!B106
A60: Main Category | B60: Sub-Category | C60: Amount
A61: Land & Legal | B61: Land Purchase | C61: =SUMIFS(Jan2026!K3:K100,Jan2026!L3:L100,$A61,Jan2026!M3:M100,$B61)+SUMIFS(Feb2026!K3:K100,Feb2026!L3:L100,$A61,Feb2026!M3:M100,$B61)+SUMIFS(Mar2026!K3:K100,Mar2026!L3:L100,$A61,Mar2026!M3:M100,$B61)+SUMIFS(Apr2026!K3:K100,Apr2026!L3:L100,$A61,Apr2026!M3:M100,$B61)+SUMIFS(May2026!K3:K100,May2026!L3:L100,$A61,May2026!M3:M100,$B61)+SUMIFS(Jun2026!K3:K100,Jun2026!L3:L100,$A61,Jun2026!M3:M100,$B61)+SUMIFS(Jul2026!K3:K100,Jul2026!L3:L100,$A61,Jul2026!M3:M100,$B61)+SUMIFS(Aug2026!K3:K100,Aug2026!L3:L100,$A61,Aug2026!M3:M100,$B61)+SUMIFS(Sep2026!K3:K100,Sep2026!L3:L100,$A61,Sep2026!M3:M100,$B61)+SUMIFS(Oct2026!K3:K100,Oct2026!L3:L100,$A61,Oct2026!M3:M100,$B61)+SUMIFS(Nov2026!K3:K100,Nov2026!L3:L100,$A61,Nov2026!M3:M100,$B61)+SUMIFS(Dec2026!K3:K100,Dec2026!L3:L100,$A61,Dec2026!M3:M100,$B61)
A62: Land & Legal | B62: Advance Payments | C62: =SUMIFS(Jan2026!K3:K100,Jan2026!L3:L100,$A62,Jan2026!M3:M100,$B62)+SUMIFS(Feb2026!K3:K100,Feb2026!L3:L100,$A62,Feb2026!M3:M100,$B62)+SUMIFS(Mar2026!K3:K100,Mar2026!L3:L100,$A62,Mar2026!M3:M100,$B62)+SUMIFS(Apr2026!K3:K100,Apr2026!L3:L100,$A62,Apr2026!M3:M100,$B62)+SUMIFS(May2026!K3:K100,May2026!L3:L100,$A62,May2026!M3:M100,$B62)+SUMIFS(Jun2026!K3:K100,Jun2026!L3:L100,$A62,Jun2026!M3:M100,$B62)+SUMIFS(Jul2026!K3:K100,Jul2026!L3:L100,$A62,Jul2026!M3:M100,$B62)+SUMIFS(Aug2026!K3:K100,Aug2026!L3:L100,$A62,Aug2026!M3:M100,$B62)+SUMIFS(Sep2026!K3:K100,Sep2026!L3:L100,$A62,Sep2026!M3:M100,$B62)+SUMIFS(Oct2026!K3:K100,Oct2026!L3:L100,$A62,Oct2026!M3:M100,$B62)+SUMIFS(Nov2026!K3:K100,Nov2026!L3:L100,$A62,Nov2026!M3:M100,$B62)+SUMIFS(Dec2026!K3:K100,Dec2026!L3:L100,$A62,Dec2026!M3:M100,$B62)
A63: Land & Legal | B63: Registration Charges | C63: =SUMIFS(Jan2026!K3:K100,Jan2026!L3:L100,$A63,Jan2026!M3:M100,$B63)+SUMIFS(Feb2026!K3:K100,Feb2026!L3:L100,$A63,Feb2026!M3:M100,$B63)+SUMIFS(Mar2026!K3:K100,Mar2026!L3:L100,$A63,Mar2026!M3:M100,$B63)+SUMIFS(Apr2026!K3:K100,Apr2026!L3:L100,$A63,Apr2026!M3:M100,$B63)+SUMIFS(May2026!K3:K100,May2026!L3:L100,$A63,May2026!M3:M100,$B63)+SUMIFS(Jun2026!K3:K100,Jun2026!L3:L100,$A63,Jun2026!M3:M100,$B63)+SUMIFS(Jul2026!K3:K100,Jul2026!L3:L100,$A63,Jul2026!M3:M100,$B63)+SUMIFS(Aug2026!K3:K100,Aug2026!L3:L100,$A63,Aug2026!M3:M100,$B63)+SUMIFS(Sep2026!K3:K100,Sep2026!L3:L100,$A63,Sep2026!M3:M100,$B63)+SUMIFS(Oct2026!K3:K100,Oct2026!L3:L100,$A63,Oct2026!M3:M100,$B63)+SUMIFS(Nov2026!K3:K100,Nov2026!L3:L100,$A63,Nov2026!M3:M100,$B63)+SUMIFS(Dec2026!K3:K100,Dec2026!L3:L100,$A63,Dec2026!M3:M100,$B63)
A64: Land & Legal | B64: Stamp Duty | C64: =SUMIFS(Jan2026!K3:K100,Jan2026!L3:L100,$A64,Jan2026!M3:M100,$B64)+SUMIFS(Feb2026!K3:K100,Feb2026!L3:L100,$A64,Feb2026!M3:M100,$B64)+SUMIFS(Mar2026!K3:K100,Mar2026!L3:L100,$A64,Mar2026!M3:M100,$B64)+SUMIFS(Apr2026!K3:K100,Apr2026!L3:L100,$A64,Apr2026!M3:M100,$B64)+SUMIFS(May2026!K3:K100,May2026!L3:L100,$A64,May2026!M3:M100,$B64)+SUMIFS(Jun2026!K3:K100,Jun2026!L3:L100,$A64,Jun2026!M3:M100,$B64)+SUMIFS(Jul2026!K3:K100,Jul2026!L3:L100,$A64,Jul2026!M3:M100,$B64)+SUMIFS(Aug2026!K3:K100,Aug2026!L3:L100,$A64,Aug2026!M3:M100,$B64)+SUMIFS(Sep2026!K3:K100,Sep2026!L3:L100,$A64,Sep2026!M3:M100,$B64)+SUMIFS(Oct2026!K3:K100,Oct2026!L3:L100,$A64,Oct2026!M3:M100,$B64)+SUMIFS(Nov2026!K3:K100,Nov2026!L3:L100,$A64,Nov2026!M3:M100,$B64)+SUMIFS(Dec2026!K3:K100,Dec2026!L3:L100,$A64,Dec2026!M3:M100,$B64)
A65: Land & Legal | B65: Legal Fees | C65: =SUMIFS(Jan2026!K3:K100,Jan2026!L3:L100,$A65,Jan2026!M3:M100,$B65)+SUMIFS(Feb2026!K3:K100,Feb2026!L3:L100,$A65,Feb2026!M3:M100,$B65)+SUMIFS(Mar2026!K3:K100,Mar2026!L3:L100,$A65,Mar2026!M3:M100,$B65)+SUMIFS(Apr2026!K3:K100,Apr2026!L3:L100,$A65,Apr2026!M3:M100,$B65)+SUMIFS(May2026!K3:K100,May2026!L3:L100,$A65,May2026!M3:M100,$B65)+SUMIFS(Jun2026!K3:K100,Jun2026!L3:L100,$A65,Jun2026!M3:M100,$B65)+SUMIFS(Jul2026!K3:K100,Jul2026!L3:L100,$A65,Jul2026!M3:M100,$B65)+SUMIFS(Aug2026!K3:K100,Aug2026!L3:L100,$A65,Aug2026!M3:M100,$B65)+SUMIFS(Sep2026!K3:K100,Sep2026!L3:L100,$A65,Sep2026!M3:M100,$B65)+SUMIFS(Oct2026!K3:K100,Oct2026!L3:L100,$A65,Oct2026!M3:M100,$B65)+SUMIFS(Nov2026!K3:K100,Nov2026!L3:L100,$A65,Nov2026!M3:M100,$B65)+SUMIFS(Dec2026!K3:K100,Dec2026!L3:L100,$A65,Dec2026!M3:M100,$B65)
A66: Land & Legal | B66: Survey Charges | C66: =SUMIFS(Jan2026!K3:K100,Jan2026!L3:L100,$A66,Jan2026!M3:M100,$B66)+SUMIFS(Feb2026!K3:K100,Feb2026!L3:L100,$A66,Feb2026!M3:M100,$B66)+SUMIFS(Mar2026!K3:K100,Mar2026!L3:L100,$A66,Mar2026!M3:M100,$B66)+SUMIFS(Apr2026!K3:K100,Apr2026!L3:L100,$A66,Apr2026!M3:M100,$B66)+SUMIFS(May2026!K3:K100,May2026!L3:L100,$A66,May2026!M3:M100,$B66)+SUMIFS(Jun2026!K3:K100,Jun2026!L3:L100,$A66,Jun2026!M3:M100,$B66)+SUMIFS(Jul2026!K3:K100,Jul2026!L3:L100,$A66,Jul2026!M3:M100,$B66)+SUMIFS(Aug2026!K3:K100,Aug2026!L3:L100,$A66,Aug2026!M3:M100,$B66)+SUMIFS(Sep2026!K3:K100,Sep2026!L3:L100,$A66,Sep2026!M3:M100,$B66)+SUMIFS(Oct2026!K3:K100,Oct2026!L3:L100,$A66,Oct2026!M3:M100,$B66)+SUMIFS(Nov2026!K3:K100,Nov2026!L3:L100,$A66,Nov2026!M3:M100,$B66)+SUMIFS(Dec2026!K3:K100,Dec2026!L3:L100,$A66,Dec2026!M3:M100,$B66)
A67: Land & Legal | B67: Documentation | C67: =SUMIFS(Jan2026!K3:K100,Jan2026!L3:L100,$A67,Jan2026!M3:M100,$B67)+SUMIFS(Feb2026!K3:K100,Feb2026!L3:L100,$A67,Feb2026!M3:M100,$B67)+SUMIFS(Mar2026!K3:K100,Mar2026!L3:L100,$A67,Mar2026!M3:M100,$B67)+SUMIFS(Apr2026!K3:K100,Apr2026!L3:L100,$A67,Apr2026!M3:M100,$B67)+SUMIFS(May2026!K3:K100,May2026!L3:L100,$A67,May2026!M3:M100,$B67)+SUMIFS(Jun2026!K3:K100,Jun2026!L3:L100,$A67,Jun2026!M3:M100,$B67)+SUMIFS(Jul2026!K3:K100,Jul2026!L3:L100,$A67,Jul2026!M3:M100,$B67)+SUMIFS(Aug2026!K3:K100,Aug2026!L3:L100,$A67,Aug2026!M3:M100,$B67)+SUMIFS(Sep2026!K3:K100,Sep2026!L3:L100,$A67,Sep2026!M3:M100,$B67)+SUMIFS(Oct2026!K3:K100,Oct2026!L3:L100,$A67,Oct2026!M3:M100,$B67)+SUMIFS(Nov2026!K3:K100,Nov2026!L3:L100,$A67,Nov2026!M3:M100,$B67)+SUMIFS(Dec2026!K3:K100,Dec2026!L3:L100,$A67,Dec2026!M3:M100,$B67)
A68: Site Development | B68: Land Clearing | C68: =SUMIFS(Jan2026!K3:K100,Jan2026!L3:L100,$A68,Jan2026!M3:M100,$B68)+SUMIFS(Feb2026!K3:K100,Feb2026!L3:L100,$A68,Feb2026!M3:M100,$B68)+SUMIFS(Mar2026!K3:K100,Mar2026!L3:L100,$A68,Mar2026!M3:M100,$B68)+SUMIFS(Apr2026!K3:K100,Apr2026!L3:L100,$A68,Apr2026!M3:M100,$B68)+SUMIFS(May2026!K3:K100,May2026!L3:L100,$A68,May2026!M3:M100,$B68)+SUMIFS(Jun2026!K3:K100,Jun2026!L3:L100,$A68,Jun2026!M3:M100,$B68)+SUMIFS(Jul2026!K3:K100,Jul2026!L3:L100,$A68,Jul2026!M3:M100,$B68)+SUMIFS(Aug2026!K3:K100,Aug2026!L3:L100,$A68,Aug2026!M3:M100,$B68)+SUMIFS(Sep2026!K3:K100,Sep2026!L3:L100,$A68,Sep2026!M3:M100,$B68)+SUMIFS(Oct2026!K3:K100,Oct2026!L3:L100,$A68,Oct2026!M3:M100,$B68)+SUMIFS(Nov2026!K3:K100,Nov2026!L3:L100,$A68,Nov2026!M3:M100,$B68)+SUMIFS(Dec2026!K3:K100,Dec2026!L3:L100,$A68,Dec2026!M3:M100,$B68)
A69: Site Development | B69: Earthwork & Levelling | C69: =SUMIFS(Jan2026!K3:K100,Jan2026!L3:L100,$A69,Jan2026!M3:M100,$B69)+SUMIFS(Feb2026!K3:K100,Feb2026!L3:L100,$A69,Feb2026!M3:M100,$B69)+SUMIFS(Mar2026!K3:K100,Mar2026!L3:L100,$A69,Mar2026!M3:M100,$B69)+SUMIFS(Apr2026!K3:K100,Apr2026!L3:L100,$A69,Apr2026!M3:M100,$B69)+SUMIFS(May2026!K3:K100,May2026!L3:L100,$A69,May2026!M3:M100,$B69)+SUMIFS(Jun2026!K3:K100,Jun2026!L3:L100,$A69,Jun2026!M3:M100,$B69)+SUMIFS(Jul2026!K3:K100,Jul2026!L3:L100,$A69,Jul2026!M3:M100,$B69)+SUMIFS(Aug2026!K3:K100,Aug2026!L3:L100,$A69,Aug2026!M3:M100,$B69)+SUMIFS(Sep2026!K3:K100,Sep2026!L3:L100,$A69,Sep2026!M3:M100,$B69)+SUMIFS(Oct2026!K3:K100,Oct2026!L3:L100,$A69,Oct2026!M3:M100,$B69)+SUMIFS(Nov2026!K3:K100,Nov2026!L3:L100,$A69,Nov2026!M3:M100,$B69)+SUMIFS(Dec2026!K3:K100,Dec2026!L3:L100,$A69,Dec2026!M3:M100,$B69)
A70: Site Development | B70: Road Formation | C70: =SUMIFS(Jan2026!K3:K100,Jan2026!L3:L100,$A70,Jan2026!M3:M100,$B70)+SUMIFS(Feb2026!K3:K100,Feb2026!L3:L100,$A70,Feb2026!M3:M100,$B70)+SUMIFS(Mar2026!K3:K100,Mar2026!L3:L100,$A70,Mar2026!M3:M100,$B70)+SUMIFS(Apr2026!K3:K100,Apr2026!L3:L100,$A70,Apr2026!M3:M100,$B70)+SUMIFS(May2026!K3:K100,May2026!L3:L100,$A70,May2026!M3:M100,$B70)+SUMIFS(Jun2026!K3:K100,Jun2026!L3:L100,$A70,Jun2026!M3:M100,$B70)+SUMIFS(Jul2026!K3:K100,Jul2026!L3:L100,$A70,Jul2026!M3:M100,$B70)+SUMIFS(Aug2026!K3:K100,Aug2026!L3:L100,$A70,Aug2026!M3:M100,$B70)+SUMIFS(Sep2026!K3:K100,Sep2026!L3:L100,$A70,Sep2026!M3:M100,$B70)+SUMIFS(Oct2026!K3:K100,Oct2026!L3:L100,$A70,Oct2026!M3:M100,$B70)+SUMIFS(Nov2026!K3:K100,Nov2026!L3:L100,$A70,Nov2026!M3:M100,$B70)+SUMIFS(Dec2026!K3:K100,Dec2026!L3:L100,$A70,Dec2026!M3:M100,$B70)
A71: Site Development | B71: Blacktop Roads | C71: =SUMIFS(Jan2026!K3:K100,Jan2026!L3:L100,$A71,Jan2026!M3:M100,$B71)+SUMIFS(Feb2026!K3:K100,Feb2026!L3:L100,$A71,Feb2026!M3:M100,$B71)+SUMIFS(Mar2026!K3:K100,Mar2026!L3:L100,$A71,Mar2026!M3:M100,$B71)+SUMIFS(Apr2026!K3:K100,Apr2026!L3:L100,$A71,Apr2026!M3:M100,$B71)+SUMIFS(May2026!K3:K100,May2026!L3:L100,$A71,May2026!M3:M100,$B71)+SUMIFS(Jun2026!K3:K100,Jun2026!L3:L100,$A71,Jun2026!M3:M100,$B71)+SUMIFS(Jul2026!K3:K100,Jul2026!L3:L100,$A71,Jul2026!M3:M100,$B71)+SUMIFS(Aug2026!K3:K100,Aug2026!L3:L100,$A71,Aug2026!M3:M100,$B71)+SUMIFS(Sep2026!K3:K100,Sep2026!L3:L100,$A71,Sep2026!M3:M100,$B71)+SUMIFS(Oct2026!K3:K100,Oct2026!L3:L100,$A71,Oct2026!M3:M100,$B71)+SUMIFS(Nov2026!K3:K100,Nov2026!L3:L100,$A71,Nov2026!M3:M100,$B71)+SUMIFS(Dec2026!K3:K100,Dec2026!L3:L100,$A71,Dec2026!M3:M100,$B71)
A72: Site Development | B72: Interlocking Pavers | C72: =SUMIFS(Jan2026!K3:K100,Jan2026!L3:L100,$A72,Jan2026!M3:M100,$B72)+SUMIFS(Feb2026!K3:K100,Feb2026!L3:L100,$A72,Feb2026!M3:M100,$B72)+SUMIFS(Mar2026!K3:K100,Mar2026!L3:L100,$A72,Mar2026!M3:M100,$B72)+SUMIFS(Apr2026!K3:K100,Apr2026!L3:L100,$A72,Apr2026!M3:M100,$B72)+SUMIFS(May2026!K3:K100,May2026!L3:L100,$A72,May2026!M3:M100,$B72)+SUMIFS(Jun2026!K3:K100,Jun2026!L3:L100,$A72,Jun2026!M3:M100,$B72)+SUMIFS(Jul2026!K3:K100,Jul2026!L3:L100,$A72,Jul2026!M3:M100,$B72)+SUMIFS(Aug2026!K3:K100,Aug2026!L3:L100,$A72,Aug2026!M3:M100,$B72)+SUMIFS(Sep2026!K3:K100,Sep2026!L3:L100,$A72,Sep2026!M3:M100,$B72)+SUMIFS(Oct2026!K3:K100,Oct2026!L3:L100,$A72,Oct2026!M3:M100,$B72)+SUMIFS(Nov2026!K3:K100,Nov2026!L3:L100,$A72,Nov2026!M3:M100,$B72)+SUMIFS(Dec2026!K3:K100,Dec2026!L3:L100,$A72,Dec2026!M3:M100,$B72)
A73: Site Development | B73: Compound Wall | C73: =SUMIFS(Jan2026!K3:K100,Jan2026!L3:L100,$A73,Jan2026!M3:M100,$B73)+SUMIFS(Feb2026!K3:K100,Feb2026!L3:L100,$A73,Feb2026!M3:M100,$B73)+SUMIFS(Mar2026!K3:K100,Mar2026!L3:L100,$A73,Mar2026!M3:M100,$B73)+SUMIFS(Apr2026!K3:K100,Apr2026!L3:L100,$A73,Apr2026!M3:M100,$B73)+SUMIFS(May2026!K3:K100,May2026!L3:L100,$A73,May2026!M3:M100,$B73)+SUMIFS(Jun2026!K3:K100,Jun2026!L3:L100,$A73,Jun2026!M3:M100,$B73)+SUMIFS(Jul2026!K3:K100,Jul2026!L3:L100,$A73,Jul2026!M3:M100,$B73)+SUMIFS(Aug2026!K3:K100,Aug2026!L3:L100,$A73,Aug2026!M3:M100,$B73)+SUMIFS(Sep2026!K3:K100,Sep2026!L3:L100,$A73,Sep2026!M3:M100,$B73)+SUMIFS(Oct2026!K3:K100,Oct2026!L3:L100,$A73,Oct2026!M3:M100,$B73)+SUMIFS(Nov2026!K3:K100,Nov2026!L3:L100,$A73,Nov2026!M3:M100,$B73)+SUMIFS(Dec2026!K3:K100,Dec2026!L3:L100,$A73,Dec2026!M3:M100,$B73)
A74: Site Development | B74: Entrance Gate | C74: =SUMIFS(Jan2026!K3:K100,Jan2026!L3:L100,$A74,Jan2026!M3:M100,$B74)+SUMIFS(Feb2026!K3:K100,Feb2026!L3:L100,$A74,Feb2026!M3:M100,$B74)+SUMIFS(Mar2026!K3:K100,Mar2026!L3:L100,$A74,Mar2026!M3:M100,$B74)+SUMIFS(Apr2026!K3:K100,Apr2026!L3:L100,$A74,Apr2026!M3:M100,$B74)+SUMIFS(May2026!K3:K100,May2026!L3:L100,$A74,May2026!M3:M100,$B74)+SUMIFS(Jun2026!K3:K100,Jun2026!L3:L100,$A74,Jun2026!M3:M100,$B74)+SUMIFS(Jul2026!K3:K100,Jul2026!L3:L100,$A74,Jul2026!M3:M100,$B74)+SUMIFS(Aug2026!K3:K100,Aug2026!L3:L100,$A74,Aug2026!M3:M100,$B74)+SUMIFS(Sep2026!K3:K100,Sep2026!L3:L100,$A74,Sep2026!M3:M100,$B74)+SUMIFS(Oct2026!K3:K100,Oct2026!L3:L100,$A74,Oct2026!M3:M100,$B74)+SUMIFS(Nov2026!K3:K100,Nov2026!L3:L100,$A74,Nov2026!M3:M100,$B74)+SUMIFS(Dec2026!K3:K100,Dec2026!L3:L100,$A74,Dec2026!M3:M100,$B74)
A75: Site Development | B75: Drainage | C75: =SUMIFS(Jan2026!K3:K100,Jan2026!L3:L100,$A75,Jan2026!M3:M100,$B75)+SUMIFS(Feb2026!K3:K100,Feb2026!L3:L100,$A75,Feb2026!M3:M100,$B75)+SUMIFS(Mar2026!K3:K100,Mar2026!L3:L100,$A75,Mar2026!M3:M100,$B75)+SUMIFS(Apr2026!K3:K100,Apr2026!L3:L100,$A75,Apr2026!M3:M100,$B75)+SUMIFS(May2026!K3:K100,May2026!L3:L100,$A75,May2026!M3:M100,$B75)+SUMIFS(Jun2026!K3:K100,Jun2026!L3:L100,$A75,Jun2026!M3:M100,$B75)+SUMIFS(Jul2026!K3:K100,Jul2026!L3:L100,$A75,Jul2026!M3:M100,$B75)+SUMIFS(Aug2026!K3:K100,Aug2026!L3:L100,$A75,Aug2026!M3:M100,$B75)+SUMIFS(Sep2026!K3:K100,Sep2026!L3:L100,$A75,Sep2026!M3:M100,$B75)+SUMIFS(Oct2026!K3:K100,Oct2026!L3:L100,$A75,Oct2026!M3:M100,$B75)+SUMIFS(Nov2026!K3:K100,Nov2026!L3:L100,$A75,Nov2026!M3:M100,$B75)+SUMIFS(Dec2026!K3:K100,Dec2026!L3:L100,$A75,Dec2026!M3:M100,$B75)
A76: Site Development | B76: Culverts | C76: =SUMIFS(Jan2026!K3:K100,Jan2026!L3:L100,$A76,Jan2026!M3:M100,$B76)+SUMIFS(Feb2026!K3:K100,Feb2026!L3:L100,$A76,Feb2026!M3:M100,$B76)+SUMIFS(Mar2026!K3:K100,Mar2026!L3:L100,$A76,Mar2026!M3:M100,$B76)+SUMIFS(Apr2026!K3:K100,Apr2026!L3:L100,$A76,Apr2026!M3:M100,$B76)+SUMIFS(May2026!K3:K100,May2026!L3:L100,$A76,May2026!M3:M100,$B76)+SUMIFS(Jun2026!K3:K100,Jun2026!L3:L100,$A76,Jun2026!M3:M100,$B76)+SUMIFS(Jul2026!K3:K100,Jul2026!L3:L100,$A76,Jul2026!M3:M100,$B76)+SUMIFS(Aug2026!K3:K100,Aug2026!L3:L100,$A76,Aug2026!M3:M100,$B76)+SUMIFS(Sep2026!K3:K100,Sep2026!L3:L100,$A76,Sep2026!M3:M100,$B76)+SUMIFS(Oct2026!K3:K100,Oct2026!L3:L100,$A76,Oct2026!M3:M100,$B76)+SUMIFS(Nov2026!K3:K100,Nov2026!L3:L100,$A76,Nov2026!M3:M100,$B76)+SUMIFS(Dec2026!K3:K100,Dec2026!L3:L100,$A76,Dec2026!M3:M100,$B76)
A77: Utilities | B77: Borewell | C77: =SUMIFS(Jan2026!K3:K100,Jan2026!L3:L100,$A77,Jan2026!M3:M100,$B77)+SUMIFS(Feb2026!K3:K100,Feb2026!L3:L100,$A77,Feb2026!M3:M100,$B77)+SUMIFS(Mar2026!K3:K100,Mar2026!L3:L100,$A77,Mar2026!M3:M100,$B77)+SUMIFS(Apr2026!K3:K100,Apr2026!L3:L100,$A77,Apr2026!M3:M100,$B77)+SUMIFS(May2026!K3:K100,May2026!L3:L100,$A77,May2026!M3:M100,$B77)+SUMIFS(Jun2026!K3:K100,Jun2026!L3:L100,$A77,Jun2026!M3:M100,$B77)+SUMIFS(Jul2026!K3:K100,Jul2026!L3:L100,$A77,Jul2026!M3:M100,$B77)+SUMIFS(Aug2026!K3:K100,Aug2026!L3:L100,$A77,Aug2026!M3:M100,$B77)+SUMIFS(Sep2026!K3:K100,Sep2026!L3:L100,$A77,Sep2026!M3:M100,$B77)+SUMIFS(Oct2026!K3:K100,Oct2026!L3:L100,$A77,Oct2026!M3:M100,$B77)+SUMIFS(Nov2026!K3:K100,Nov2026!L3:L100,$A77,Nov2026!M3:M100,$B77)+SUMIFS(Dec2026!K3:K100,Dec2026!L3:L100,$A77,Dec2026!M3:M100,$B77)
A78: Utilities | B78: Water Pipelines | C78: =SUMIFS(Jan2026!K3:K100,Jan2026!L3:L100,$A78,Jan2026!M3:M100,$B78)+SUMIFS(Feb2026!K3:K100,Feb2026!L3:L100,$A78,Feb2026!M3:M100,$B78)+SUMIFS(Mar2026!K3:K100,Mar2026!L3:L100,$A78,Mar2026!M3:M100,$B78)+SUMIFS(Apr2026!K3:K100,Apr2026!L3:L100,$A78,Apr2026!M3:M100,$B78)+SUMIFS(May2026!K3:K100,May2026!L3:L100,$A78,May2026!M3:M100,$B78)+SUMIFS(Jun2026!K3:K100,Jun2026!L3:L100,$A78,Jun2026!M3:M100,$B78)+SUMIFS(Jul2026!K3:K100,Jul2026!L3:L100,$A78,Jul2026!M3:M100,$B78)+SUMIFS(Aug2026!K3:K100,Aug2026!L3:L100,$A78,Aug2026!M3:M100,$B78)+SUMIFS(Sep2026!K3:K100,Sep2026!L3:L100,$A78,Sep2026!M3:M100,$B78)+SUMIFS(Oct2026!K3:K100,Oct2026!L3:L100,$A78,Oct2026!M3:M100,$B78)+SUMIFS(Nov2026!K3:K100,Nov2026!L3:L100,$A78,Nov2026!M3:M100,$B78)+SUMIFS(Dec2026!K3:K100,Dec2026!L3:L100,$A78,Dec2026!M3:M100,$B78)
A79: Utilities | B79: Water Tank | C79: =SUMIFS(Jan2026!K3:K100,Jan2026!L3:L100,$A79,Jan2026!M3:M100,$B79)+SUMIFS(Feb2026!K3:K100,Feb2026!L3:L100,$A79,Feb2026!M3:M100,$B79)+SUMIFS(Mar2026!K3:K100,Mar2026!L3:L100,$A79,Mar2026!M3:M100,$B79)+SUMIFS(Apr2026!K3:K100,Apr2026!L3:L100,$A79,Apr2026!M3:M100,$B79)+SUMIFS(May2026!K3:K100,May2026!L3:L100,$A79,May2026!M3:M100,$B79)+SUMIFS(Jun2026!K3:K100,Jun2026!L3:L100,$A79,Jun2026!M3:M100,$B79)+SUMIFS(Jul2026!K3:K100,Jul2026!L3:L100,$A79,Jul2026!M3:M100,$B79)+SUMIFS(Aug2026!K3:K100,Aug2026!L3:L100,$A79,Aug2026!M3:M100,$B79)+SUMIFS(Sep2026!K3:K100,Sep2026!L3:L100,$A79,Sep2026!M3:M100,$B79)+SUMIFS(Oct2026!K3:K100,Oct2026!L3:L100,$A79,Oct2026!M3:M100,$B79)+SUMIFS(Nov2026!K3:K100,Nov2026!L3:L100,$A79,Nov2026!M3:M100,$B79)+SUMIFS(Dec2026!K3:K100,Dec2026!L3:L100,$A79,Dec2026!M3:M100,$B79)
A80: Utilities | B80: Electricity Connection | C80: =SUMIFS(Jan2026!K3:K100,Jan2026!L3:L100,$A80,Jan2026!M3:M100,$B80)+SUMIFS(Feb2026!K3:K100,Feb2026!L3:L100,$A80,Feb2026!M3:M100,$B80)+SUMIFS(Mar2026!K3:K100,Mar2026!L3:L100,$A80,Mar2026!M3:M100,$B80)+SUMIFS(Apr2026!K3:K100,Apr2026!L3:L100,$A80,Apr2026!M3:M100,$B80)+SUMIFS(May2026!K3:K100,May2026!L3:L100,$A80,May2026!M3:M100,$B80)+SUMIFS(Jun2026!K3:K100,Jun2026!L3:L100,$A80,Jun2026!M3:M100,$B80)+SUMIFS(Jul2026!K3:K100,Jul2026!L3:L100,$A80,Jul2026!M3:M100,$B80)+SUMIFS(Aug2026!K3:K100,Aug2026!L3:L100,$A80,Aug2026!M3:M100,$B80)+SUMIFS(Sep2026!K3:K100,Sep2026!L3:L100,$A80,Sep2026!M3:M100,$B80)+SUMIFS(Oct2026!K3:K100,Oct2026!L3:L100,$A80,Oct2026!M3:M100,$B80)+SUMIFS(Nov2026!K3:K100,Nov2026!L3:L100,$A80,Nov2026!M3:M100,$B80)+SUMIFS(Dec2026!K3:K100,Dec2026!L3:L100,$A80,Dec2026!M3:M100,$B80)
A81: Utilities | B81: Transformer | C81: =SUMIFS(Jan2026!K3:K100,Jan2026!L3:L100,$A81,Jan2026!M3:M100,$B81)+SUMIFS(Feb2026!K3:K100,Feb2026!L3:L100,$A81,Feb2026!M3:M100,$B81)+SUMIFS(Mar2026!K3:K100,Mar2026!L3:L100,$A81,Mar2026!M3:M100,$B81)+SUMIFS(Apr2026!K3:K100,Apr2026!L3:L100,$A81,Apr2026!M3:M100,$B81)+SUMIFS(May2026!K3:K100,May2026!L3:L100,$A81,May2026!M3:M100,$B81)+SUMIFS(Jun2026!K3:K100,Jun2026!L3:L100,$A81,Jun2026!M3:M100,$B81)+SUMIFS(Jul2026!K3:K100,Jul2026!L3:L100,$A81,Jul2026!M3:M100,$B81)+SUMIFS(Aug2026!K3:K100,Aug2026!L3:L100,$A81,Aug2026!M3:M100,$B81)+SUMIFS(Sep2026!K3:K100,Sep2026!L3:L100,$A81,Sep2026!M3:M100,$B81)+SUMIFS(Oct2026!K3:K100,Oct2026!L3:L100,$A81,Oct2026!M3:M100,$B81)+SUMIFS(Nov2026!K3:K100,Nov2026!L3:L100,$A81,Nov2026!M3:M100,$B81)+SUMIFS(Dec2026!K3:K100,Dec2026!L3:L100,$A81,Dec2026!M3:M100,$B81)
A82: Utilities | B82: Street Lights | C82: =SUMIFS(Jan2026!K3:K100,Jan2026!L3:L100,$A82,Jan2026!M3:M100,$B82)+SUMIFS(Feb2026!K3:K100,Feb2026!L3:L100,$A82,Feb2026!M3:M100,$B82)+SUMIFS(Mar2026!K3:K100,Mar2026!L3:L100,$A82,Mar2026!M3:M100,$B82)+SUMIFS(Apr2026!K3:K100,Apr2026!L3:L100,$A82,Apr2026!M3:M100,$B82)+SUMIFS(May2026!K3:K100,May2026!L3:L100,$A82,May2026!M3:M100,$B82)+SUMIFS(Jun2026!K3:K100,Jun2026!L3:L100,$A82,Jun2026!M3:M100,$B82)+SUMIFS(Jul2026!K3:K100,Jul2026!L3:L100,$A82,Jul2026!M3:M100,$B82)+SUMIFS(Aug2026!K3:K100,Aug2026!L3:L100,$A82,Aug2026!M3:M100,$B82)+SUMIFS(Sep2026!K3:K100,Sep2026!L3:L100,$A82,Sep2026!M3:M100,$B82)+SUMIFS(Oct2026!K3:K100,Oct2026!L3:L100,$A82,Oct2026!M3:M100,$B82)+SUMIFS(Nov2026!K3:K100,Nov2026!L3:L100,$A82,Nov2026!M3:M100,$B82)+SUMIFS(Dec2026!K3:K100,Dec2026!L3:L100,$A82,Dec2026!M3:M100,$B82)
A83: Utilities | B83: Generator | C83: =SUMIFS(Jan2026!K3:K100,Jan2026!L3:L100,$A83,Jan2026!M3:M100,$B83)+SUMIFS(Feb2026!K3:K100,Feb2026!L3:L100,$A83,Feb2026!M3:M100,$B83)+SUMIFS(Mar2026!K3:K100,Mar2026!L3:L100,$A83,Mar2026!M3:M100,$B83)+SUMIFS(Apr2026!K3:K100,Apr2026!L3:L100,$A83,Apr2026!M3:M100,$B83)+SUMIFS(May2026!K3:K100,May2026!L3:L100,$A83,May2026!M3:M100,$B83)+SUMIFS(Jun2026!K3:K100,Jun2026!L3:L100,$A83,Jun2026!M3:M100,$B83)+SUMIFS(Jul2026!K3:K100,Jul2026!L3:L100,$A83,Jul2026!M3:M100,$B83)+SUMIFS(Aug2026!K3:K100,Aug2026!L3:L100,$A83,Aug2026!M3:M100,$B83)+SUMIFS(Sep2026!K3:K100,Sep2026!L3:L100,$A83,Sep2026!M3:M100,$B83)+SUMIFS(Oct2026!K3:K100,Oct2026!L3:L100,$A83,Oct2026!M3:M100,$B83)+SUMIFS(Nov2026!K3:K100,Nov2026!L3:L100,$A83,Nov2026!M3:M100,$B83)+SUMIFS(Dec2026!K3:K100,Dec2026!L3:L100,$A83,Dec2026!M3:M100,$B83)
A84: Landscaping | B84: Plantation | C84: =SUMIFS(Jan2026!K3:K100,Jan2026!L3:L100,$A84,Jan2026!M3:M100,$B84)+SUMIFS(Feb2026!K3:K100,Feb2026!L3:L100,$A84,Feb2026!M3:M100,$B84)+SUMIFS(Mar2026!K3:K100,Mar2026!L3:L100,$A84,Mar2026!M3:M100,$B84)+SUMIFS(Apr2026!K3:K100,Apr2026!L3:L100,$A84,Apr2026!M3:M100,$B84)+SUMIFS(May2026!K3:K100,May2026!L3:L100,$A84,May2026!M3:M100,$B84)+SUMIFS(Jun2026!K3:K100,Jun2026!L3:L100,$A84,Jun2026!M3:M100,$B84)+SUMIFS(Jul2026!K3:K100,Jul2026!L3:L100,$A84,Jul2026!M3:M100,$B84)+SUMIFS(Aug2026!K3:K100,Aug2026!L3:L100,$A84,Aug2026!M3:M100,$B84)+SUMIFS(Sep2026!K3:K100,Sep2026!L3:L100,$A84,Sep2026!M3:M100,$B84)+SUMIFS(Oct2026!K3:K100,Oct2026!L3:L100,$A84,Oct2026!M3:M100,$B84)+SUMIFS(Nov2026!K3:K100,Nov2026!L3:L100,$A84,Nov2026!M3:M100,$B84)+SUMIFS(Dec2026!K3:K100,Dec2026!L3:L100,$A84,Dec2026!M3:M100,$B84)
A85: Landscaping | B85: Miyawaki Forest | C85: =SUMIFS(Jan2026!K3:K100,Jan2026!L3:L100,$A85,Jan2026!M3:M100,$B85)+SUMIFS(Feb2026!K3:K100,Feb2026!L3:L100,$A85,Feb2026!M3:M100,$B85)+SUMIFS(Mar2026!K3:K100,Mar2026!L3:L100,$A85,Mar2026!M3:M100,$B85)+SUMIFS(Apr2026!K3:K100,Apr2026!L3:L100,$A85,Apr2026!M3:M100,$B85)+SUMIFS(May2026!K3:K100,May2026!L3:L100,$A85,May2026!M3:M100,$B85)+SUMIFS(Jun2026!K3:K100,Jun2026!L3:L100,$A85,Jun2026!M3:M100,$B85)+SUMIFS(Jul2026!K3:K100,Jul2026!L3:L100,$A85,Jul2026!M3:M100,$B85)+SUMIFS(Aug2026!K3:K100,Aug2026!L3:L100,$A85,Aug2026!M3:M100,$B85)+SUMIFS(Sep2026!K3:K100,Sep2026!L3:L100,$A85,Sep2026!M3:M100,$B85)+SUMIFS(Oct2026!K3:K100,Oct2026!L3:L100,$A85,Oct2026!M3:M100,$B85)+SUMIFS(Nov2026!K3:K100,Nov2026!L3:L100,$A85,Nov2026!M3:M100,$B85)+SUMIFS(Dec2026!K3:K100,Dec2026!L3:L100,$A85,Dec2026!M3:M100,$B85)
A86: Landscaping | B86: Lawn Development | C86: =SUMIFS(Jan2026!K3:K100,Jan2026!L3:L100,$A86,Jan2026!M3:M100,$B86)+SUMIFS(Feb2026!K3:K100,Feb2026!L3:L100,$A86,Feb2026!M3:M100,$B86)+SUMIFS(Mar2026!K3:K100,Mar2026!L3:L100,$A86,Mar2026!M3:M100,$B86)+SUMIFS(Apr2026!K3:K100,Apr2026!L3:L100,$A86,Apr2026!M3:M100,$B86)+SUMIFS(May2026!K3:K100,May2026!L3:L100,$A86,May2026!M3:M100,$B86)+SUMIFS(Jun2026!K3:K100,Jun2026!L3:L100,$A86,Jun2026!M3:M100,$B86)+SUMIFS(Jul2026!K3:K100,Jul2026!L3:L100,$A86,Jul2026!M3:M100,$B86)+SUMIFS(Aug2026!K3:K100,Aug2026!L3:L100,$A86,Aug2026!M3:M100,$B86)+SUMIFS(Sep2026!K3:K100,Sep2026!L3:L100,$A86,Sep2026!M3:M100,$B86)+SUMIFS(Oct2026!K3:K100,Oct2026!L3:L100,$A86,Oct2026!M3:M100,$B86)+SUMIFS(Nov2026!K3:K100,Nov2026!L3:L100,$A86,Nov2026!M3:M100,$B86)+SUMIFS(Dec2026!K3:K100,Dec2026!L3:L100,$A86,Dec2026!M3:M100,$B86)
A87: Landscaping | B87: Irrigation/Drip System | C87: =SUMIFS(Jan2026!K3:K100,Jan2026!L3:L100,$A87,Jan2026!M3:M100,$B87)+SUMIFS(Feb2026!K3:K100,Feb2026!L3:L100,$A87,Feb2026!M3:M100,$B87)+SUMIFS(Mar2026!K3:K100,Mar2026!L3:L100,$A87,Mar2026!M3:M100,$B87)+SUMIFS(Apr2026!K3:K100,Apr2026!L3:L100,$A87,Apr2026!M3:M100,$B87)+SUMIFS(May2026!K3:K100,May2026!L3:L100,$A87,May2026!M3:M100,$B87)+SUMIFS(Jun2026!K3:K100,Jun2026!L3:L100,$A87,Jun2026!M3:M100,$B87)+SUMIFS(Jul2026!K3:K100,Jul2026!L3:L100,$A87,Jul2026!M3:M100,$B87)+SUMIFS(Aug2026!K3:K100,Aug2026!L3:L100,$A87,Aug2026!M3:M100,$B87)+SUMIFS(Sep2026!K3:K100,Sep2026!L3:L100,$A87,Sep2026!M3:M100,$B87)+SUMIFS(Oct2026!K3:K100,Oct2026!L3:L100,$A87,Oct2026!M3:M100,$B87)+SUMIFS(Nov2026!K3:K100,Nov2026!L3:L100,$A87,Nov2026!M3:M100,$B87)+SUMIFS(Dec2026!K3:K100,Dec2026!L3:L100,$A87,Dec2026!M3:M100,$B87)
A88: Landscaping | B88: Garden Maintenance | C88: =SUMIFS(Jan2026!K3:K100,Jan2026!L3:L100,$A88,Jan2026!M3:M100,$B88)+SUMIFS(Feb2026!K3:K100,Feb2026!L3:L100,$A88,Feb2026!M3:M100,$B88)+SUMIFS(Mar2026!K3:K100,Mar2026!L3:L100,$A88,Mar2026!M3:M100,$B88)+SUMIFS(Apr2026!K3:K100,Apr2026!L3:L100,$A88,Apr2026!M3:M100,$B88)+SUMIFS(May2026!K3:K100,May2026!L3:L100,$A88,May2026!M3:M100,$B88)+SUMIFS(Jun2026!K3:K100,Jun2026!L3:L100,$A88,Jun2026!M3:M100,$B88)+SUMIFS(Jul2026!K3:K100,Jul2026!L3:L100,$A88,Jul2026!M3:M100,$B88)+SUMIFS(Aug2026!K3:K100,Aug2026!L3:L100,$A88,Aug2026!M3:M100,$B88)+SUMIFS(Sep2026!K3:K100,Sep2026!L3:L100,$A88,Sep2026!M3:M100,$B88)+SUMIFS(Oct2026!K3:K100,Oct2026!L3:L100,$A88,Oct2026!M3:M100,$B88)+SUMIFS(Nov2026!K3:K100,Nov2026!L3:L100,$A88,Nov2026!M3:M100,$B88)+SUMIFS(Dec2026!K3:K100,Dec2026!L3:L100,$A88,Dec2026!M3:M100,$B88)
A89: Buildings & Amenities | B89: Security Room | C89: =SUMIFS(Jan2026!K3:K100,Jan2026!L3:L100,$A89,Jan2026!M3:M100,$B89)+SUMIFS(Feb2026!K3:K100,Feb2026!L3:L100,$A89,Feb2026!M3:M100,$B89)+SUMIFS(Mar2026!K3:K100,Mar2026!L3:L100,$A89,Mar2026!M3:M100,$B89)+SUMIFS(Apr2026!K3:K100,Apr2026!L3:L100,$A89,Apr2026!M3:M100,$B89)+SUMIFS(May2026!K3:K100,May2026!L3:L100,$A89,May2026!M3:M100,$B89)+SUMIFS(Jun2026!K3:K100,Jun2026!L3:L100,$A89,Jun2026!M3:M100,$B89)+SUMIFS(Jul2026!K3:K100,Jul2026!L3:L100,$A89,Jul2026!M3:M100,$B89)+SUMIFS(Aug2026!K3:K100,Aug2026!L3:L100,$A89,Aug2026!M3:M100,$B89)+SUMIFS(Sep2026!K3:K100,Sep2026!L3:L100,$A89,Sep2026!M3:M100,$B89)+SUMIFS(Oct2026!K3:K100,Oct2026!L3:L100,$A89,Oct2026!M3:M100,$B89)+SUMIFS(Nov2026!K3:K100,Nov2026!L3:L100,$A89,Nov2026!M3:M100,$B89)+SUMIFS(Dec2026!K3:K100,Dec2026!L3:L100,$A89,Dec2026!M3:M100,$B89)
A90: Buildings & Amenities | B90: Site Office | C90: =SUMIFS(Jan2026!K3:K100,Jan2026!L3:L100,$A90,Jan2026!M3:M100,$B90)+SUMIFS(Feb2026!K3:K100,Feb2026!L3:L100,$A90,Feb2026!M3:M100,$B90)+SUMIFS(Mar2026!K3:K100,Mar2026!L3:L100,$A90,Mar2026!M3:M100,$B90)+SUMIFS(Apr2026!K3:K100,Apr2026!L3:L100,$A90,Apr2026!M3:M100,$B90)+SUMIFS(May2026!K3:K100,May2026!L3:L100,$A90,May2026!M3:M100,$B90)+SUMIFS(Jun2026!K3:K100,Jun2026!L3:L100,$A90,Jun2026!M3:M100,$B90)+SUMIFS(Jul2026!K3:K100,Jul2026!L3:L100,$A90,Jul2026!M3:M100,$B90)+SUMIFS(Aug2026!K3:K100,Aug2026!L3:L100,$A90,Aug2026!M3:M100,$B90)+SUMIFS(Sep2026!K3:K100,Sep2026!L3:L100,$A90,Sep2026!M3:M100,$B90)+SUMIFS(Oct2026!K3:K100,Oct2026!L3:L100,$A90,Oct2026!M3:M100,$B90)+SUMIFS(Nov2026!K3:K100,Nov2026!L3:L100,$A90,Nov2026!M3:M100,$B90)+SUMIFS(Dec2026!K3:K100,Dec2026!L3:L100,$A90,Dec2026!M3:M100,$B90)
A91: Buildings & Amenities | B91: Clubhouse | C91: =SUMIFS(Jan2026!K3:K100,Jan2026!L3:L100,$A91,Jan2026!M3:M100,$B91)+SUMIFS(Feb2026!K3:K100,Feb2026!L3:L100,$A91,Feb2026!M3:M100,$B91)+SUMIFS(Mar2026!K3:K100,Mar2026!L3:L100,$A91,Mar2026!M3:M100,$B91)+SUMIFS(Apr2026!K3:K100,Apr2026!L3:L100,$A91,Apr2026!M3:M100,$B91)+SUMIFS(May2026!K3:K100,May2026!L3:L100,$A91,May2026!M3:M100,$B91)+SUMIFS(Jun2026!K3:K100,Jun2026!L3:L100,$A91,Jun2026!M3:M100,$B91)+SUMIFS(Jul2026!K3:K100,Jul2026!L3:L100,$A91,Jul2026!M3:M100,$B91)+SUMIFS(Aug2026!K3:K100,Aug2026!L3:L100,$A91,Aug2026!M3:M100,$B91)+SUMIFS(Sep2026!K3:K100,Sep2026!L3:L100,$A91,Sep2026!M3:M100,$B91)+SUMIFS(Oct2026!K3:K100,Oct2026!L3:L100,$A91,Oct2026!M3:M100,$B91)+SUMIFS(Nov2026!K3:K100,Nov2026!L3:L100,$A91,Nov2026!M3:M100,$B91)+SUMIFS(Dec2026!K3:K100,Dec2026!L3:L100,$A91,Dec2026!M3:M100,$B91)
A92: Buildings & Amenities | B92: Swimming Pool | C92: =SUMIFS(Jan2026!K3:K100,Jan2026!L3:L100,$A92,Jan2026!M3:M100,$B92)+SUMIFS(Feb2026!K3:K100,Feb2026!L3:L100,$A92,Feb2026!M3:M100,$B92)+SUMIFS(Mar2026!K3:K100,Mar2026!L3:L100,$A92,Mar2026!M3:M100,$B92)+SUMIFS(Apr2026!K3:K100,Apr2026!L3:L100,$A92,Apr2026!M3:M100,$B92)+SUMIFS(May2026!K3:K100,May2026!L3:L100,$A92,May2026!M3:M100,$B92)+SUMIFS(Jun2026!K3:K100,Jun2026!L3:L100,$A92,Jun2026!M3:M100,$B92)+SUMIFS(Jul2026!K3:K100,Jul2026!L3:L100,$A92,Jul2026!M3:M100,$B92)+SUMIFS(Aug2026!K3:K100,Aug2026!L3:L100,$A92,Aug2026!M3:M100,$B92)+SUMIFS(Sep2026!K3:K100,Sep2026!L3:L100,$A92,Sep2026!M3:M100,$B92)+SUMIFS(Oct2026!K3:K100,Oct2026!L3:L100,$A92,Oct2026!M3:M100,$B92)+SUMIFS(Nov2026!K3:K100,Nov2026!L3:L100,$A92,Nov2026!M3:M100,$B92)+SUMIFS(Dec2026!K3:K100,Dec2026!L3:L100,$A92,Dec2026!M3:M100,$B92)
A93: Buildings & Amenities | B93: Gazebo | C93: =SUMIFS(Jan2026!K3:K100,Jan2026!L3:L100,$A93,Jan2026!M3:M100,$B93)+SUMIFS(Feb2026!K3:K100,Feb2026!L3:L100,$A93,Feb2026!M3:M100,$B93)+SUMIFS(Mar2026!K3:K100,Mar2026!L3:L100,$A93,Mar2026!M3:M100,$B93)+SUMIFS(Apr2026!K3:K100,Apr2026!L3:L100,$A93,Apr2026!M3:M100,$B93)+SUMIFS(May2026!K3:K100,May2026!L3:L100,$A93,May2026!M3:M100,$B93)+SUMIFS(Jun2026!K3:K100,Jun2026!L3:L100,$A93,Jun2026!M3:M100,$B93)+SUMIFS(Jul2026!K3:K100,Jul2026!L3:L100,$A93,Jul2026!M3:M100,$B93)+SUMIFS(Aug2026!K3:K100,Aug2026!L3:L100,$A93,Aug2026!M3:M100,$B93)+SUMIFS(Sep2026!K3:K100,Sep2026!L3:L100,$A93,Sep2026!M3:M100,$B93)+SUMIFS(Oct2026!K3:K100,Oct2026!L3:L100,$A93,Oct2026!M3:M100,$B93)+SUMIFS(Nov2026!K3:K100,Nov2026!L3:L100,$A93,Nov2026!M3:M100,$B93)+SUMIFS(Dec2026!K3:K100,Dec2026!L3:L100,$A93,Dec2026!M3:M100,$B93)
A94: Buildings & Amenities | B94: Children's Play Area | C94: =SUMIFS(Jan2026!K3:K100,Jan2026!L3:L100,$A94,Jan2026!M3:M100,$B94)+SUMIFS(Feb2026!K3:K100,Feb2026!L3:L100,$A94,Feb2026!M3:M100,$B94)+SUMIFS(Mar2026!K3:K100,Mar2026!L3:L100,$A94,Mar2026!M3:M100,$B94)+SUMIFS(Apr2026!K3:K100,Apr2026!L3:L100,$A94,Apr2026!M3:M100,$B94)+SUMIFS(May2026!K3:K100,May2026!L3:L100,$A94,May2026!M3:M100,$B94)+SUMIFS(Jun2026!K3:K100,Jun2026!L3:L100,$A94,Jun2026!M3:M100,$B94)+SUMIFS(Jul2026!K3:K100,Jul2026!L3:L100,$A94,Jul2026!M3:M100,$B94)+SUMIFS(Aug2026!K3:K100,Aug2026!L3:L100,$A94,Aug2026!M3:M100,$B94)+SUMIFS(Sep2026!K3:K100,Sep2026!L3:L100,$A94,Sep2026!M3:M100,$B94)+SUMIFS(Oct2026!K3:K100,Oct2026!L3:L100,$A94,Oct2026!M3:M100,$B94)+SUMIFS(Nov2026!K3:K100,Nov2026!L3:L100,$A94,Nov2026!M3:M100,$B94)+SUMIFS(Dec2026!K3:K100,Dec2026!L3:L100,$A94,Dec2026!M3:M100,$B94)
A95: Buildings & Amenities | B95: Sports Courts | C95: =SUMIFS(Jan2026!K3:K100,Jan2026!L3:L100,$A95,Jan2026!M3:M100,$B95)+SUMIFS(Feb2026!K3:K100,Feb2026!L3:L100,$A95,Feb2026!M3:M100,$B95)+SUMIFS(Mar2026!K3:K100,Mar2026!L3:L100,$A95,Mar2026!M3:M100,$B95)+SUMIFS(Apr2026!K3:K100,Apr2026!L3:L100,$A95,Apr2026!M3:M100,$B95)+SUMIFS(May2026!K3:K100,May2026!L3:L100,$A95,May2026!M3:M100,$B95)+SUMIFS(Jun2026!K3:K100,Jun2026!L3:L100,$A95,Jun2026!M3:M100,$B95)+SUMIFS(Jul2026!K3:K100,Jul2026!L3:L100,$A95,Jul2026!M3:M100,$B95)+SUMIFS(Aug2026!K3:K100,Aug2026!L3:L100,$A95,Aug2026!M3:M100,$B95)+SUMIFS(Sep2026!K3:K100,Sep2026!L3:L100,$A95,Sep2026!M3:M100,$B95)+SUMIFS(Oct2026!K3:K100,Oct2026!L3:L100,$A95,Oct2026!M3:M100,$B95)+SUMIFS(Nov2026!K3:K100,Nov2026!L3:L100,$A95,Nov2026!M3:M100,$B95)+SUMIFS(Dec2026!K3:K100,Dec2026!L3:L100,$A95,Dec2026!M3:M100,$B95)
A96: Buildings & Amenities | B96: Toilets | C96: =SUMIFS(Jan2026!K3:K100,Jan2026!L3:L100,$A96,Jan2026!M3:M100,$B96)+SUMIFS(Feb2026!K3:K100,Feb2026!L3:L100,$A96,Feb2026!M3:M100,$B96)+SUMIFS(Mar2026!K3:K100,Mar2026!L3:L100,$A96,Mar2026!M3:M100,$B96)+SUMIFS(Apr2026!K3:K100,Apr2026!L3:L100,$A96,Apr2026!M3:M100,$B96)+SUMIFS(May2026!K3:K100,May2026!L3:L100,$A96,May2026!M3:M100,$B96)+SUMIFS(Jun2026!K3:K100,Jun2026!L3:L100,$A96,Jun2026!M3:M100,$B96)+SUMIFS(Jul2026!K3:K100,Jul2026!L3:L100,$A96,Jul2026!M3:M100,$B96)+SUMIFS(Aug2026!K3:K100,Aug2026!L3:L100,$A96,Aug2026!M3:M100,$B96)+SUMIFS(Sep2026!K3:K100,Sep2026!L3:L100,$A96,Sep2026!M3:M100,$B96)+SUMIFS(Oct2026!K3:K100,Oct2026!L3:L100,$A96,Oct2026!M3:M100,$B96)+SUMIFS(Nov2026!K3:K100,Nov2026!L3:L100,$A96,Nov2026!M3:M100,$B96)+SUMIFS(Dec2026!K3:K100,Dec2026!L3:L100,$A96,Dec2026!M3:M100,$B96)
A97: Labour & Contractors | B97: Labour Wages | C97: =SUMIFS(Jan2026!K3:K100,Jan2026!L3:L100,$A97,Jan2026!M3:M100,$B97)+SUMIFS(Feb2026!K3:K100,Feb2026!L3:L100,$A97,Feb2026!M3:M100,$B97)+SUMIFS(Mar2026!K3:K100,Mar2026!L3:L100,$A97,Mar2026!M3:M100,$B97)+SUMIFS(Apr2026!K3:K100,Apr2026!L3:L100,$A97,Apr2026!M3:M100,$B97)+SUMIFS(May2026!K3:K100,May2026!L3:L100,$A97,May2026!M3:M100,$B97)+SUMIFS(Jun2026!K3:K100,Jun2026!L3:L100,$A97,Jun2026!M3:M100,$B97)+SUMIFS(Jul2026!K3:K100,Jul2026!L3:L100,$A97,Jul2026!M3:M100,$B97)+SUMIFS(Aug2026!K3:K100,Aug2026!L3:L100,$A97,Aug2026!M3:M100,$B97)+SUMIFS(Sep2026!K3:K100,Sep2026!L3:L100,$A97,Sep2026!M3:M100,$B97)+SUMIFS(Oct2026!K3:K100,Oct2026!L3:L100,$A97,Oct2026!M3:M100,$B97)+SUMIFS(Nov2026!K3:K100,Nov2026!L3:L100,$A97,Nov2026!M3:M100,$B97)+SUMIFS(Dec2026!K3:K100,Dec2026!L3:L100,$A97,Dec2026!M3:M100,$B97)
A98: Labour & Contractors | B98: Contractor Payments | C98: =SUMIFS(Jan2026!K3:K100,Jan2026!L3:L100,$A98,Jan2026!M3:M100,$B98)+SUMIFS(Feb2026!K3:K100,Feb2026!L3:L100,$A98,Feb2026!M3:M100,$B98)+SUMIFS(Mar2026!K3:K100,Mar2026!L3:L100,$A98,Mar2026!M3:M100,$B98)+SUMIFS(Apr2026!K3:K100,Apr2026!L3:L100,$A98,Apr2026!M3:M100,$B98)+SUMIFS(May2026!K3:K100,May2026!L3:L100,$A98,May2026!M3:M100,$B98)+SUMIFS(Jun2026!K3:K100,Jun2026!L3:L100,$A98,Jun2026!M3:M100,$B98)+SUMIFS(Jul2026!K3:K100,Jul2026!L3:L100,$A98,Jul2026!M3:M100,$B98)+SUMIFS(Aug2026!K3:K100,Aug2026!L3:L100,$A98,Aug2026!M3:M100,$B98)+SUMIFS(Sep2026!K3:K100,Sep2026!L3:L100,$A98,Sep2026!M3:M100,$B98)+SUMIFS(Oct2026!K3:K100,Oct2026!L3:L100,$A98,Oct2026!M3:M100,$B98)+SUMIFS(Nov2026!K3:K100,Nov2026!L3:L100,$A98,Nov2026!M3:M100,$B98)+SUMIFS(Dec2026!K3:K100,Dec2026!L3:L100,$A98,Dec2026!M3:M100,$B98)
A99: Labour & Contractors | B99: Machinery Hire | C99: =SUMIFS(Jan2026!K3:K100,Jan2026!L3:L100,$A99,Jan2026!M3:M100,$B99)+SUMIFS(Feb2026!K3:K100,Feb2026!L3:L100,$A99,Feb2026!M3:M100,$B99)+SUMIFS(Mar2026!K3:K100,Mar2026!L3:L100,$A99,Mar2026!M3:M100,$B99)+SUMIFS(Apr2026!K3:K100,Apr2026!L3:L100,$A99,Apr2026!M3:M100,$B99)+SUMIFS(May2026!K3:K100,May2026!L3:L100,$A99,May2026!M3:M100,$B99)+SUMIFS(Jun2026!K3:K100,Jun2026!L3:L100,$A99,Jun2026!M3:M100,$B99)+SUMIFS(Jul2026!K3:K100,Jul2026!L3:L100,$A99,Jul2026!M3:M100,$B99)+SUMIFS(Aug2026!K3:K100,Aug2026!L3:L100,$A99,Aug2026!M3:M100,$B99)+SUMIFS(Sep2026!K3:K100,Sep2026!L3:L100,$A99,Sep2026!M3:M100,$B99)+SUMIFS(Oct2026!K3:K100,Oct2026!L3:L100,$A99,Oct2026!M3:M100,$B99)+SUMIFS(Nov2026!K3:K100,Nov2026!L3:L100,$A99,Nov2026!M3:M100,$B99)+SUMIFS(Dec2026!K3:K100,Dec2026!L3:L100,$A99,Dec2026!M3:M100,$B99)
A100: Labour & Contractors | B100: Excavator/JCB | C100: =SUMIFS(Jan2026!K3:K100,Jan2026!L3:L100,$A100,Jan2026!M3:M100,$B100)+SUMIFS(Feb2026!K3:K100,Feb2026!L3:L100,$A100,Feb2026!M3:M100,$B100)+SUMIFS(Mar2026!K3:K100,Mar2026!L3:L100,$A100,Mar2026!M3:M100,$B100)+SUMIFS(Apr2026!K3:K100,Apr2026!L3:L100,$A100,Apr2026!M3:M100,$B100)+SUMIFS(May2026!K3:K100,May2026!L3:L100,$A100,May2026!M3:M100,$B100)+SUMIFS(Jun2026!K3:K100,Jun2026!L3:L100,$A100,Jun2026!M3:M100,$B100)+SUMIFS(Jul2026!K3:K100,Jul2026!L3:L100,$A100,Jul2026!M3:M100,$B100)+SUMIFS(Aug2026!K3:K100,Aug2026!L3:L100,$A100,Aug2026!M3:M100,$B100)+SUMIFS(Sep2026!K3:K100,Sep2026!L3:L100,$A100,Sep2026!M3:M100,$B100)+SUMIFS(Oct2026!K3:K100,Oct2026!L3:L100,$A100,Oct2026!M3:M100,$B100)+SUMIFS(Nov2026!K3:K100,Nov2026!L3:L100,$A100,Nov2026!M3:M100,$B100)+SUMIFS(Dec2026!K3:K100,Dec2026!L3:L100,$A100,Dec2026!M3:M100,$B100)
A101: Labour & Contractors | B101: Tractor & Transport | C101: =SUMIFS(Jan2026!K3:K100,Jan2026!L3:L100,$A101,Jan2026!M3:M100,$B101)+SUMIFS(Feb2026!K3:K100,Feb2026!L3:L100,$A101,Feb2026!M3:M100,$B101)+SUMIFS(Mar2026!K3:K100,Mar2026!L3:L100,$A101,Mar2026!M3:M100,$B101)+SUMIFS(Apr2026!K3:K100,Apr2026!L3:L100,$A101,Apr2026!M3:M100,$B101)+SUMIFS(May2026!K3:K100,May2026!L3:L100,$A101,May2026!M3:M100,$B101)+SUMIFS(Jun2026!K3:K100,Jun2026!L3:L100,$A101,Jun2026!M3:M100,$B101)+SUMIFS(Jul2026!K3:K100,Jul2026!L3:L100,$A101,Jul2026!M3:M100,$B101)+SUMIFS(Aug2026!K3:K100,Aug2026!L3:L100,$A101,Aug2026!M3:M100,$B101)+SUMIFS(Sep2026!K3:K100,Sep2026!L3:L100,$A101,Sep2026!M3:M100,$B101)+SUMIFS(Oct2026!K3:K100,Oct2026!L3:L100,$A101,Oct2026!M3:M100,$B101)+SUMIFS(Nov2026!K3:K100,Nov2026!L3:L100,$A101,Nov2026!M3:M100,$B101)+SUMIFS(Dec2026!K3:K100,Dec2026!L3:L100,$A101,Dec2026!M3:M100,$B101)
A102: Materials | B102: Cement | C102: =SUMIFS(Jan2026!K3:K100,Jan2026!L3:L100,$A102,Jan2026!M3:M100,$B102)+SUMIFS(Feb2026!K3:K100,Feb2026!L3:L100,$A102,Feb2026!M3:M100,$B102)+SUMIFS(Mar2026!K3:K100,Mar2026!L3:L100,$A102,Mar2026!M3:M100,$B102)+SUMIFS(Apr2026!K3:K100,Apr2026!L3:L100,$A102,Apr2026!M3:M100,$B102)+SUMIFS(May2026!K3:K100,May2026!L3:L100,$A102,May2026!M3:M100,$B102)+SUMIFS(Jun2026!K3:K100,Jun2026!L3:L100,$A102,Jun2026!M3:M100,$B102)+SUMIFS(Jul2026!K3:K100,Jul2026!L3:L100,$A102,Jul2026!M3:M100,$B102)+SUMIFS(Aug2026!K3:K100,Aug2026!L3:L100,$A102,Aug2026!M3:M100,$B102)+SUMIFS(Sep2026!K3:K100,Sep2026!L3:L100,$A102,Sep2026!M3:M100,$B102)+SUMIFS(Oct2026!K3:K100,Oct2026!L3:L100,$A102,Oct2026!M3:M100,$B102)+SUMIFS(Nov2026!K3:K100,Nov2026!L3:L100,$A102,Nov2026!M3:M100,$B102)+SUMIFS(Dec2026!K3:K100,Dec2026!L3:L100,$A102,Dec2026!M3:M100,$B102)
A103: Materials | B103: Sand | C103: =SUMIFS(Jan2026!K3:K100,Jan2026!L3:L100,$A103,Jan2026!M3:M100,$B103)+SUMIFS(Feb2026!K3:K100,Feb2026!L3:L100,$A103,Feb2026!M3:M100,$B103)+SUMIFS(Mar2026!K3:K100,Mar2026!L3:L100,$A103,Mar2026!M3:M100,$B103)+SUMIFS(Apr2026!K3:K100,Apr2026!L3:L100,$A103,Apr2026!M3:M100,$B103)+SUMIFS(May2026!K3:K100,May2026!L3:L100,$A103,May2026!M3:M100,$B103)+SUMIFS(Jun2026!K3:K100,Jun2026!L3:L100,$A103,Jun2026!M3:M100,$B103)+SUMIFS(Jul2026!K3:K100,Jul2026!L3:L100,$A103,Jul2026!M3:M100,$B103)+SUMIFS(Aug2026!K3:K100,Aug2026!L3:L100,$A103,Aug2026!M3:M100,$B103)+SUMIFS(Sep2026!K3:K100,Sep2026!L3:L100,$A103,Sep2026!M3:M100,$B103)+SUMIFS(Oct2026!K3:K100,Oct2026!L3:L100,$A103,Oct2026!M3:M100,$B103)+SUMIFS(Nov2026!K3:K100,Nov2026!L3:L100,$A103,Nov2026!M3:M100,$B103)+SUMIFS(Dec2026!K3:K100,Dec2026!L3:L100,$A103,Dec2026!M3:M100,$B103)
A104: Materials | B104: Metal | C104: =SUMIFS(Jan2026!K3:K100,Jan2026!L3:L100,$A104,Jan2026!M3:M100,$B104)+SUMIFS(Feb2026!K3:K100,Feb2026!L3:L100,$A104,Feb2026!M3:M100,$B104)+SUMIFS(Mar2026!K3:K100,Mar2026!L3:L100,$A104,Mar2026!M3:M100,$B104)+SUMIFS(Apr2026!K3:K100,Apr2026!L3:L100,$A104,Apr2026!M3:M100,$B104)+SUMIFS(May2026!K3:K100,May2026!L3:L100,$A104,May2026!M3:M100,$B104)+SUMIFS(Jun2026!K3:K100,Jun2026!L3:L100,$A104,Jun2026!M3:M100,$B104)+SUMIFS(Jul2026!K3:K100,Jul2026!L3:L100,$A104,Jul2026!M3:M100,$B104)+SUMIFS(Aug2026!K3:K100,Aug2026!L3:L100,$A104,Aug2026!M3:M100,$B104)+SUMIFS(Sep2026!K3:K100,Sep2026!L3:L100,$A104,Sep2026!M3:M100,$B104)+SUMIFS(Oct2026!K3:K100,Oct2026!L3:L100,$A104,Oct2026!M3:M100,$B104)+SUMIFS(Nov2026!K3:K100,Nov2026!L3:L100,$A104,Nov2026!M3:M100,$B104)+SUMIFS(Dec2026!K3:K100,Dec2026!L3:L100,$A104,Dec2026!M3:M100,$B104)
A105: Materials | B105: Bricks | C105: =SUMIFS(Jan2026!K3:K100,Jan2026!L3:L100,$A105,Jan2026!M3:M100,$B105)+SUMIFS(Feb2026!K3:K100,Feb2026!L3:L100,$A105,Feb2026!M3:M100,$B105)+SUMIFS(Mar2026!K3:K100,Mar2026!L3:L100,$A105,Mar2026!M3:M100,$B105)+SUMIFS(Apr2026!K3:K100,Apr2026!L3:L100,$A105,Apr2026!M3:M100,$B105)+SUMIFS(May2026!K3:K100,May2026!L3:L100,$A105,May2026!M3:M100,$B105)+SUMIFS(Jun2026!K3:K100,Jun2026!L3:L100,$A105,Jun2026!M3:M100,$B105)+SUMIFS(Jul2026!K3:K100,Jul2026!L3:L100,$A105,Jul2026!M3:M100,$B105)+SUMIFS(Aug2026!K3:K100,Aug2026!L3:L100,$A105,Aug2026!M3:M100,$B105)+SUMIFS(Sep2026!K3:K100,Sep2026!L3:L100,$A105,Sep2026!M3:M100,$B105)+SUMIFS(Oct2026!K3:K100,Oct2026!L3:L100,$A105,Oct2026!M3:M100,$B105)+SUMIFS(Nov2026!K3:K100,Nov2026!L3:L100,$A105,Nov2026!M3:M100,$B105)+SUMIFS(Dec2026!K3:K100,Dec2026!L3:L100,$A105,Dec2026!M3:M100,$B105)
A106: Materials | B106: Steel | C106: =SUMIFS(Jan2026!K3:K100,Jan2026!L3:L100,$A106,Jan2026!M3:M100,$B106)+SUMIFS(Feb2026!K3:K100,Feb2026!L3:L100,$A106,Feb2026!M3:M100,$B106)+SUMIFS(Mar2026!K3:K100,Mar2026!L3:L100,$A106,Mar2026!M3:M100,$B106)+SUMIFS(Apr2026!K3:K100,Apr2026!L3:L100,$A106,Apr2026!M3:M100,$B106)+SUMIFS(May2026!K3:K100,May2026!L3:L100,$A106,May2026!M3:M100,$B106)+SUMIFS(Jun2026!K3:K100,Jun2026!L3:L100,$A106,Jun2026!M3:M100,$B106)+SUMIFS(Jul2026!K3:K100,Jul2026!L3:L100,$A106,Jul2026!M3:M100,$B106)+SUMIFS(Aug2026!K3:K100,Aug2026!L3:L100,$A106,Aug2026!M3:M100,$B106)+SUMIFS(Sep2026!K3:K100,Sep2026!L3:L100,$A106,Sep2026!M3:M100,$B106)+SUMIFS(Oct2026!K3:K100,Oct2026!L3:L100,$A106,Oct2026!M3:M100,$B106)+SUMIFS(Nov2026!K3:K100,Nov2026!L3:L100,$A106,Nov2026!M3:M100,$B106)+SUMIFS(Dec2026!K3:K100,Dec2026!L3:L100,$A106,Dec2026!M3:M100,$B106)
A107: Materials | B107: Pipes | C107: =SUMIFS(Jan2026!K3:K100,Jan2026!L3:L100,$A107,Jan2026!M3:M100,$B107)+SUMIFS(Feb2026!K3:K100,Feb2026!L3:L100,$A107,Feb2026!M3:M100,$B107)+SUMIFS(Mar2026!K3:K100,Mar2026!L3:L100,$A107,Mar2026!M3:M100,$B107)+SUMIFS(Apr2026!K3:K100,Apr2026!L3:L100,$A107,Apr2026!M3:M100,$B107)+SUMIFS(May2026!K3:K100,May2026!L3:L100,$A107,May2026!M3:M100,$B107)+SUMIFS(Jun2026!K3:K100,Jun2026!L3:L100,$A107,Jun2026!M3:M100,$B107)+SUMIFS(Jul2026!K3:K100,Jul2026!L3:L100,$A107,Jul2026!M3:M100,$B107)+SUMIFS(Aug2026!K3:K100,Aug2026!L3:L100,$A107,Aug2026!M3:M100,$B107)+SUMIFS(Sep2026!K3:K100,Sep2026!L3:L100,$A107,Sep2026!M3:M100,$B107)+SUMIFS(Oct2026!K3:K100,Oct2026!L3:L100,$A107,Oct2026!M3:M100,$B107)+SUMIFS(Nov2026!K3:K100,Nov2026!L3:L100,$A107,Nov2026!M3:M100,$B107)+SUMIFS(Dec2026!K3:K100,Dec2026!L3:L100,$A107,Dec2026!M3:M100,$B107)
A108: Materials | B108: Electrical Materials | C108: =SUMIFS(Jan2026!K3:K100,Jan2026!L3:L100,$A108,Jan2026!M3:M100,$B108)+SUMIFS(Feb2026!K3:K100,Feb2026!L3:L100,$A108,Feb2026!M3:M100,$B108)+SUMIFS(Mar2026!K3:K100,Mar2026!L3:L100,$A108,Mar2026!M3:M100,$B108)+SUMIFS(Apr2026!K3:K100,Apr2026!L3:L100,$A108,Apr2026!M3:M100,$B108)+SUMIFS(May2026!K3:K100,May2026!L3:L100,$A108,May2026!M3:M100,$B108)+SUMIFS(Jun2026!K3:K100,Jun2026!L3:L100,$A108,Jun2026!M3:M100,$B108)+SUMIFS(Jul2026!K3:K100,Jul2026!L3:L100,$A108,Jul2026!M3:M100,$B108)+SUMIFS(Aug2026!K3:K100,Aug2026!L3:L100,$A108,Aug2026!M3:M100,$B108)+SUMIFS(Sep2026!K3:K100,Sep2026!L3:L100,$A108,Sep2026!M3:M100,$B108)+SUMIFS(Oct2026!K3:K100,Oct2026!L3:L100,$A108,Oct2026!M3:M100,$B108)+SUMIFS(Nov2026!K3:K100,Nov2026!L3:L100,$A108,Nov2026!M3:M100,$B108)+SUMIFS(Dec2026!K3:K100,Dec2026!L3:L100,$A108,Dec2026!M3:M100,$B108)
A109: Materials | B109: Paint | C109: =SUMIFS(Jan2026!K3:K100,Jan2026!L3:L100,$A109,Jan2026!M3:M100,$B109)+SUMIFS(Feb2026!K3:K100,Feb2026!L3:L100,$A109,Feb2026!M3:M100,$B109)+SUMIFS(Mar2026!K3:K100,Mar2026!L3:L100,$A109,Mar2026!M3:M100,$B109)+SUMIFS(Apr2026!K3:K100,Apr2026!L3:L100,$A109,Apr2026!M3:M100,$B109)+SUMIFS(May2026!K3:K100,May2026!L3:L100,$A109,May2026!M3:M100,$B109)+SUMIFS(Jun2026!K3:K100,Jun2026!L3:L100,$A109,Jun2026!M3:M100,$B109)+SUMIFS(Jul2026!K3:K100,Jul2026!L3:L100,$A109,Jul2026!M3:M100,$B109)+SUMIFS(Aug2026!K3:K100,Aug2026!L3:L100,$A109,Aug2026!M3:M100,$B109)+SUMIFS(Sep2026!K3:K100,Sep2026!L3:L100,$A109,Sep2026!M3:M100,$B109)+SUMIFS(Oct2026!K3:K100,Oct2026!L3:L100,$A109,Oct2026!M3:M100,$B109)+SUMIFS(Nov2026!K3:K100,Nov2026!L3:L100,$A109,Nov2026!M3:M100,$B109)+SUMIFS(Dec2026!K3:K100,Dec2026!L3:L100,$A109,Dec2026!M3:M100,$B109)
A110: Materials | B110: Tiles | C110: =SUMIFS(Jan2026!K3:K100,Jan2026!L3:L100,$A110,Jan2026!M3:M100,$B110)+SUMIFS(Feb2026!K3:K100,Feb2026!L3:L100,$A110,Feb2026!M3:M100,$B110)+SUMIFS(Mar2026!K3:K100,Mar2026!L3:L100,$A110,Mar2026!M3:M100,$B110)+SUMIFS(Apr2026!K3:K100,Apr2026!L3:L100,$A110,Apr2026!M3:M100,$B110)+SUMIFS(May2026!K3:K100,May2026!L3:L100,$A110,May2026!M3:M100,$B110)+SUMIFS(Jun2026!K3:K100,Jun2026!L3:L100,$A110,Jun2026!M3:M100,$B110)+SUMIFS(Jul2026!K3:K100,Jul2026!L3:L100,$A110,Jul2026!M3:M100,$B110)+SUMIFS(Aug2026!K3:K100,Aug2026!L3:L100,$A110,Aug2026!M3:M100,$B110)+SUMIFS(Sep2026!K3:K100,Sep2026!L3:L100,$A110,Sep2026!M3:M100,$B110)+SUMIFS(Oct2026!K3:K100,Oct2026!L3:L100,$A110,Oct2026!M3:M100,$B110)+SUMIFS(Nov2026!K3:K100,Nov2026!L3:L100,$A110,Nov2026!M3:M100,$B110)+SUMIFS(Dec2026!K3:K100,Dec2026!L3:L100,$A110,Dec2026!M3:M100,$B110)
A111: Operations | B111: Security | C111: =SUMIFS(Jan2026!K3:K100,Jan2026!L3:L100,$A111,Jan2026!M3:M100,$B111)+SUMIFS(Feb2026!K3:K100,Feb2026!L3:L100,$A111,Feb2026!M3:M100,$B111)+SUMIFS(Mar2026!K3:K100,Mar2026!L3:L100,$A111,Mar2026!M3:M100,$B111)+SUMIFS(Apr2026!K3:K100,Apr2026!L3:L100,$A111,Apr2026!M3:M100,$B111)+SUMIFS(May2026!K3:K100,May2026!L3:L100,$A111,May2026!M3:M100,$B111)+SUMIFS(Jun2026!K3:K100,Jun2026!L3:L100,$A111,Jun2026!M3:M100,$B111)+SUMIFS(Jul2026!K3:K100,Jul2026!L3:L100,$A111,Jul2026!M3:M100,$B111)+SUMIFS(Aug2026!K3:K100,Aug2026!L3:L100,$A111,Aug2026!M3:M100,$B111)+SUMIFS(Sep2026!K3:K100,Sep2026!L3:L100,$A111,Sep2026!M3:M100,$B111)+SUMIFS(Oct2026!K3:K100,Oct2026!L3:L100,$A111,Oct2026!M3:M100,$B111)+SUMIFS(Nov2026!K3:K100,Nov2026!L3:L100,$A111,Nov2026!M3:M100,$B111)+SUMIFS(Dec2026!K3:K100,Dec2026!L3:L100,$A111,Dec2026!M3:M100,$B111)
A112: Operations | B112: Housekeeping | C112: =SUMIFS(Jan2026!K3:K100,Jan2026!L3:L100,$A112,Jan2026!M3:M100,$B112)+SUMIFS(Feb2026!K3:K100,Feb2026!L3:L100,$A112,Feb2026!M3:M100,$B112)+SUMIFS(Mar2026!K3:K100,Mar2026!L3:L100,$A112,Mar2026!M3:M100,$B112)+SUMIFS(Apr2026!K3:K100,Apr2026!L3:L100,$A112,Apr2026!M3:M100,$B112)+SUMIFS(May2026!K3:K100,May2026!L3:L100,$A112,May2026!M3:M100,$B112)+SUMIFS(Jun2026!K3:K100,Jun2026!L3:L100,$A112,Jun2026!M3:M100,$B112)+SUMIFS(Jul2026!K3:K100,Jul2026!L3:L100,$A112,Jul2026!M3:M100,$B112)+SUMIFS(Aug2026!K3:K100,Aug2026!L3:L100,$A112,Aug2026!M3:M100,$B112)+SUMIFS(Sep2026!K3:K100,Sep2026!L3:L100,$A112,Sep2026!M3:M100,$B112)+SUMIFS(Oct2026!K3:K100,Oct2026!L3:L100,$A112,Oct2026!M3:M100,$B112)+SUMIFS(Nov2026!K3:K100,Nov2026!L3:L100,$A112,Nov2026!M3:M100,$B112)+SUMIFS(Dec2026!K3:K100,Dec2026!L3:L100,$A112,Dec2026!M3:M100,$B112)
A113: Operations | B113: Fuel & Diesel | C113: =SUMIFS(Jan2026!K3:K100,Jan2026!L3:L100,$A113,Jan2026!M3:M100,$B113)+SUMIFS(Feb2026!K3:K100,Feb2026!L3:L100,$A113,Feb2026!M3:M100,$B113)+SUMIFS(Mar2026!K3:K100,Mar2026!L3:L100,$A113,Mar2026!M3:M100,$B113)+SUMIFS(Apr2026!K3:K100,Apr2026!L3:L100,$A113,Apr2026!M3:M100,$B113)+SUMIFS(May2026!K3:K100,May2026!L3:L100,$A113,May2026!M3:M100,$B113)+SUMIFS(Jun2026!K3:K100,Jun2026!L3:L100,$A113,Jun2026!M3:M100,$B113)+SUMIFS(Jul2026!K3:K100,Jul2026!L3:L100,$A113,Jul2026!M3:M100,$B113)+SUMIFS(Aug2026!K3:K100,Aug2026!L3:L100,$A113,Aug2026!M3:M100,$B113)+SUMIFS(Sep2026!K3:K100,Sep2026!L3:L100,$A113,Sep2026!M3:M100,$B113)+SUMIFS(Oct2026!K3:K100,Oct2026!L3:L100,$A113,Oct2026!M3:M100,$B113)+SUMIFS(Nov2026!K3:K100,Nov2026!L3:L100,$A113,Nov2026!M3:M100,$B113)+SUMIFS(Dec2026!K3:K100,Dec2026!L3:L100,$A113,Dec2026!M3:M100,$B113)
A114: Operations | B114: Vehicle Expenses | C114: =SUMIFS(Jan2026!K3:K100,Jan2026!L3:L100,$A114,Jan2026!M3:M100,$B114)+SUMIFS(Feb2026!K3:K100,Feb2026!L3:L100,$A114,Feb2026!M3:M100,$B114)+SUMIFS(Mar2026!K3:K100,Mar2026!L3:L100,$A114,Mar2026!M3:M100,$B114)+SUMIFS(Apr2026!K3:K100,Apr2026!L3:L100,$A114,Apr2026!M3:M100,$B114)+SUMIFS(May2026!K3:K100,May2026!L3:L100,$A114,May2026!M3:M100,$B114)+SUMIFS(Jun2026!K3:K100,Jun2026!L3:L100,$A114,Jun2026!M3:M100,$B114)+SUMIFS(Jul2026!K3:K100,Jul2026!L3:L100,$A114,Jul2026!M3:M100,$B114)+SUMIFS(Aug2026!K3:K100,Aug2026!L3:L100,$A114,Aug2026!M3:M100,$B114)+SUMIFS(Sep2026!K3:K100,Sep2026!L3:L100,$A114,Sep2026!M3:M100,$B114)+SUMIFS(Oct2026!K3:K100,Oct2026!L3:L100,$A114,Oct2026!M3:M100,$B114)+SUMIFS(Nov2026!K3:K100,Nov2026!L3:L100,$A114,Nov2026!M3:M100,$B114)+SUMIFS(Dec2026!K3:K100,Dec2026!L3:L100,$A114,Dec2026!M3:M100,$B114)
A115: Operations | B115: Repairs & Maintenance | C115: =SUMIFS(Jan2026!K3:K100,Jan2026!L3:L100,$A115,Jan2026!M3:M100,$B115)+SUMIFS(Feb2026!K3:K100,Feb2026!L3:L100,$A115,Feb2026!M3:M100,$B115)+SUMIFS(Mar2026!K3:K100,Mar2026!L3:L100,$A115,Mar2026!M3:M100,$B115)+SUMIFS(Apr2026!K3:K100,Apr2026!L3:L100,$A115,Apr2026!M3:M100,$B115)+SUMIFS(May2026!K3:K100,May2026!L3:L100,$A115,May2026!M3:M100,$B115)+SUMIFS(Jun2026!K3:K100,Jun2026!L3:L100,$A115,Jun2026!M3:M100,$B115)+SUMIFS(Jul2026!K3:K100,Jul2026!L3:L100,$A115,Jul2026!M3:M100,$B115)+SUMIFS(Aug2026!K3:K100,Aug2026!L3:L100,$A115,Aug2026!M3:M100,$B115)+SUMIFS(Sep2026!K3:K100,Sep2026!L3:L100,$A115,Sep2026!M3:M100,$B115)+SUMIFS(Oct2026!K3:K100,Oct2026!L3:L100,$A115,Oct2026!M3:M100,$B115)+SUMIFS(Nov2026!K3:K100,Nov2026!L3:L100,$A115,Nov2026!M3:M100,$B115)+SUMIFS(Dec2026!K3:K100,Dec2026!L3:L100,$A115,Dec2026!M3:M100,$B115)
A116: Operations | B116: Office Expenses | C116: =SUMIFS(Jan2026!K3:K100,Jan2026!L3:L100,$A116,Jan2026!M3:M100,$B116)+SUMIFS(Feb2026!K3:K100,Feb2026!L3:L100,$A116,Feb2026!M3:M100,$B116)+SUMIFS(Mar2026!K3:K100,Mar2026!L3:L100,$A116,Mar2026!M3:M100,$B116)+SUMIFS(Apr2026!K3:K100,Apr2026!L3:L100,$A116,Apr2026!M3:M100,$B116)+SUMIFS(May2026!K3:K100,May2026!L3:L100,$A116,May2026!M3:M100,$B116)+SUMIFS(Jun2026!K3:K100,Jun2026!L3:L100,$A116,Jun2026!M3:M100,$B116)+SUMIFS(Jul2026!K3:K100,Jul2026!L3:L100,$A116,Jul2026!M3:M100,$B116)+SUMIFS(Aug2026!K3:K100,Aug2026!L3:L100,$A116,Aug2026!M3:M100,$B116)+SUMIFS(Sep2026!K3:K100,Sep2026!L3:L100,$A116,Sep2026!M3:M100,$B116)+SUMIFS(Oct2026!K3:K100,Oct2026!L3:L100,$A116,Oct2026!M3:M100,$B116)+SUMIFS(Nov2026!K3:K100,Nov2026!L3:L100,$A116,Nov2026!M3:M100,$B116)+SUMIFS(Dec2026!K3:K100,Dec2026!L3:L100,$A116,Dec2026!M3:M100,$B116)
A117: Operations | B117: Internet & Phone | C117: =SUMIFS(Jan2026!K3:K100,Jan2026!L3:L100,$A117,Jan2026!M3:M100,$B117)+SUMIFS(Feb2026!K3:K100,Feb2026!L3:L100,$A117,Feb2026!M3:M100,$B117)+SUMIFS(Mar2026!K3:K100,Mar2026!L3:L100,$A117,Mar2026!M3:M100,$B117)+SUMIFS(Apr2026!K3:K100,Apr2026!L3:L100,$A117,Apr2026!M3:M100,$B117)+SUMIFS(May2026!K3:K100,May2026!L3:L100,$A117,May2026!M3:M100,$B117)+SUMIFS(Jun2026!K3:K100,Jun2026!L3:L100,$A117,Jun2026!M3:M100,$B117)+SUMIFS(Jul2026!K3:K100,Jul2026!L3:L100,$A117,Jul2026!M3:M100,$B117)+SUMIFS(Aug2026!K3:K100,Aug2026!L3:L100,$A117,Aug2026!M3:M100,$B117)+SUMIFS(Sep2026!K3:K100,Sep2026!L3:L100,$A117,Sep2026!M3:M100,$B117)+SUMIFS(Oct2026!K3:K100,Oct2026!L3:L100,$A117,Oct2026!M3:M100,$B117)+SUMIFS(Nov2026!K3:K100,Nov2026!L3:L100,$A117,Nov2026!M3:M100,$B117)+SUMIFS(Dec2026!K3:K100,Dec2026!L3:L100,$A117,Dec2026!M3:M100,$B117)
A118: Marketing & Sales | B118: Advertisement | C118: =SUMIFS(Jan2026!K3:K100,Jan2026!L3:L100,$A118,Jan2026!M3:M100,$B118)+SUMIFS(Feb2026!K3:K100,Feb2026!L3:L100,$A118,Feb2026!M3:M100,$B118)+SUMIFS(Mar2026!K3:K100,Mar2026!L3:L100,$A118,Mar2026!M3:M100,$B118)+SUMIFS(Apr2026!K3:K100,Apr2026!L3:L100,$A118,Apr2026!M3:M100,$B118)+SUMIFS(May2026!K3:K100,May2026!L3:L100,$A118,May2026!M3:M100,$B118)+SUMIFS(Jun2026!K3:K100,Jun2026!L3:L100,$A118,Jun2026!M3:M100,$B118)+SUMIFS(Jul2026!K3:K100,Jul2026!L3:L100,$A118,Jul2026!M3:M100,$B118)+SUMIFS(Aug2026!K3:K100,Aug2026!L3:L100,$A118,Aug2026!M3:M100,$B118)+SUMIFS(Sep2026!K3:K100,Sep2026!L3:L100,$A118,Sep2026!M3:M100,$B118)+SUMIFS(Oct2026!K3:K100,Oct2026!L3:L100,$A118,Oct2026!M3:M100,$B118)+SUMIFS(Nov2026!K3:K100,Nov2026!L3:L100,$A118,Nov2026!M3:M100,$B118)+SUMIFS(Dec2026!K3:K100,Dec2026!L3:L100,$A118,Dec2026!M3:M100,$B118)
A119: Marketing & Sales | B119: Flex Boards | C119: =SUMIFS(Jan2026!K3:K100,Jan2026!L3:L100,$A119,Jan2026!M3:M100,$B119)+SUMIFS(Feb2026!K3:K100,Feb2026!L3:L100,$A119,Feb2026!M3:M100,$B119)+SUMIFS(Mar2026!K3:K100,Mar2026!L3:L100,$A119,Mar2026!M3:M100,$B119)+SUMIFS(Apr2026!K3:K100,Apr2026!L3:L100,$A119,Apr2026!M3:M100,$B119)+SUMIFS(May2026!K3:K100,May2026!L3:L100,$A119,May2026!M3:M100,$B119)+SUMIFS(Jun2026!K3:K100,Jun2026!L3:L100,$A119,Jun2026!M3:M100,$B119)+SUMIFS(Jul2026!K3:K100,Jul2026!L3:L100,$A119,Jul2026!M3:M100,$B119)+SUMIFS(Aug2026!K3:K100,Aug2026!L3:L100,$A119,Aug2026!M3:M100,$B119)+SUMIFS(Sep2026!K3:K100,Sep2026!L3:L100,$A119,Sep2026!M3:M100,$B119)+SUMIFS(Oct2026!K3:K100,Oct2026!L3:L100,$A119,Oct2026!M3:M100,$B119)+SUMIFS(Nov2026!K3:K100,Nov2026!L3:L100,$A119,Nov2026!M3:M100,$B119)+SUMIFS(Dec2026!K3:K100,Dec2026!L3:L100,$A119,Dec2026!M3:M100,$B119)
A120: Marketing & Sales | B120: Brochures | C120: =SUMIFS(Jan2026!K3:K100,Jan2026!L3:L100,$A120,Jan2026!M3:M100,$B120)+SUMIFS(Feb2026!K3:K100,Feb2026!L3:L100,$A120,Feb2026!M3:M100,$B120)+SUMIFS(Mar2026!K3:K100,Mar2026!L3:L100,$A120,Mar2026!M3:M100,$B120)+SUMIFS(Apr2026!K3:K100,Apr2026!L3:L100,$A120,Apr2026!M3:M100,$B120)+SUMIFS(May2026!K3:K100,May2026!L3:L100,$A120,May2026!M3:M100,$B120)+SUMIFS(Jun2026!K3:K100,Jun2026!L3:L100,$A120,Jun2026!M3:M100,$B120)+SUMIFS(Jul2026!K3:K100,Jul2026!L3:L100,$A120,Jul2026!M3:M100,$B120)+SUMIFS(Aug2026!K3:K100,Aug2026!L3:L100,$A120,Aug2026!M3:M100,$B120)+SUMIFS(Sep2026!K3:K100,Sep2026!L3:L100,$A120,Sep2026!M3:M100,$B120)+SUMIFS(Oct2026!K3:K100,Oct2026!L3:L100,$A120,Oct2026!M3:M100,$B120)+SUMIFS(Nov2026!K3:K100,Nov2026!L3:L100,$A120,Nov2026!M3:M100,$B120)+SUMIFS(Dec2026!K3:K100,Dec2026!L3:L100,$A120,Dec2026!M3:M100,$B120)
A121: Marketing & Sales | B121: Events | C121: =SUMIFS(Jan2026!K3:K100,Jan2026!L3:L100,$A121,Jan2026!M3:M100,$B121)+SUMIFS(Feb2026!K3:K100,Feb2026!L3:L100,$A121,Feb2026!M3:M100,$B121)+SUMIFS(Mar2026!K3:K100,Mar2026!L3:L100,$A121,Mar2026!M3:M100,$B121)+SUMIFS(Apr2026!K3:K100,Apr2026!L3:L100,$A121,Apr2026!M3:M100,$B121)+SUMIFS(May2026!K3:K100,May2026!L3:L100,$A121,May2026!M3:M100,$B121)+SUMIFS(Jun2026!K3:K100,Jun2026!L3:L100,$A121,Jun2026!M3:M100,$B121)+SUMIFS(Jul2026!K3:K100,Jul2026!L3:L100,$A121,Jul2026!M3:M100,$B121)+SUMIFS(Aug2026!K3:K100,Aug2026!L3:L100,$A121,Aug2026!M3:M100,$B121)+SUMIFS(Sep2026!K3:K100,Sep2026!L3:L100,$A121,Sep2026!M3:M100,$B121)+SUMIFS(Oct2026!K3:K100,Oct2026!L3:L100,$A121,Oct2026!M3:M100,$B121)+SUMIFS(Nov2026!K3:K100,Nov2026!L3:L100,$A121,Nov2026!M3:M100,$B121)+SUMIFS(Dec2026!K3:K100,Dec2026!L3:L100,$A121,Dec2026!M3:M100,$B121)
A122: Marketing & Sales | B122: Photography & Drone | C122: =SUMIFS(Jan2026!K3:K100,Jan2026!L3:L100,$A122,Jan2026!M3:M100,$B122)+SUMIFS(Feb2026!K3:K100,Feb2026!L3:L100,$A122,Feb2026!M3:M100,$B122)+SUMIFS(Mar2026!K3:K100,Mar2026!L3:L100,$A122,Mar2026!M3:M100,$B122)+SUMIFS(Apr2026!K3:K100,Apr2026!L3:L100,$A122,Apr2026!M3:M100,$B122)+SUMIFS(May2026!K3:K100,May2026!L3:L100,$A122,May2026!M3:M100,$B122)+SUMIFS(Jun2026!K3:K100,Jun2026!L3:L100,$A122,Jun2026!M3:M100,$B122)+SUMIFS(Jul2026!K3:K100,Jul2026!L3:L100,$A122,Jul2026!M3:M100,$B122)+SUMIFS(Aug2026!K3:K100,Aug2026!L3:L100,$A122,Aug2026!M3:M100,$B122)+SUMIFS(Sep2026!K3:K100,Sep2026!L3:L100,$A122,Sep2026!M3:M100,$B122)+SUMIFS(Oct2026!K3:K100,Oct2026!L3:L100,$A122,Oct2026!M3:M100,$B122)+SUMIFS(Nov2026!K3:K100,Nov2026!L3:L100,$A122,Nov2026!M3:M100,$B122)+SUMIFS(Dec2026!K3:K100,Dec2026!L3:L100,$A122,Dec2026!M3:M100,$B122)
A123: Marketing & Sales | B123: Digital Marketing | C123: =SUMIFS(Jan2026!K3:K100,Jan2026!L3:L100,$A123,Jan2026!M3:M100,$B123)+SUMIFS(Feb2026!K3:K100,Feb2026!L3:L100,$A123,Feb2026!M3:M100,$B123)+SUMIFS(Mar2026!K3:K100,Mar2026!L3:L100,$A123,Mar2026!M3:M100,$B123)+SUMIFS(Apr2026!K3:K100,Apr2026!L3:L100,$A123,Apr2026!M3:M100,$B123)+SUMIFS(May2026!K3:K100,May2026!L3:L100,$A123,May2026!M3:M100,$B123)+SUMIFS(Jun2026!K3:K100,Jun2026!L3:L100,$A123,Jun2026!M3:M100,$B123)+SUMIFS(Jul2026!K3:K100,Jul2026!L3:L100,$A123,Jul2026!M3:M100,$B123)+SUMIFS(Aug2026!K3:K100,Aug2026!L3:L100,$A123,Aug2026!M3:M100,$B123)+SUMIFS(Sep2026!K3:K100,Sep2026!L3:L100,$A123,Sep2026!M3:M100,$B123)+SUMIFS(Oct2026!K3:K100,Oct2026!L3:L100,$A123,Oct2026!M3:M100,$B123)+SUMIFS(Nov2026!K3:K100,Nov2026!L3:L100,$A123,Nov2026!M3:M100,$B123)+SUMIFS(Dec2026!K3:K100,Dec2026!L3:L100,$A123,Dec2026!M3:M100,$B123)
A124: Miscellaneous | B124: Travel Expenses | C124: =SUMIFS(Jan2026!K3:K100,Jan2026!L3:L100,$A124,Jan2026!M3:M100,$B124)+SUMIFS(Feb2026!K3:K100,Feb2026!L3:L100,$A124,Feb2026!M3:M100,$B124)+SUMIFS(Mar2026!K3:K100,Mar2026!L3:L100,$A124,Mar2026!M3:M100,$B124)+SUMIFS(Apr2026!K3:K100,Apr2026!L3:L100,$A124,Apr2026!M3:M100,$B124)+SUMIFS(May2026!K3:K100,May2026!L3:L100,$A124,May2026!M3:M100,$B124)+SUMIFS(Jun2026!K3:K100,Jun2026!L3:L100,$A124,Jun2026!M3:M100,$B124)+SUMIFS(Jul2026!K3:K100,Jul2026!L3:L100,$A124,Jul2026!M3:M100,$B124)+SUMIFS(Aug2026!K3:K100,Aug2026!L3:L100,$A124,Aug2026!M3:M100,$B124)+SUMIFS(Sep2026!K3:K100,Sep2026!L3:L100,$A124,Sep2026!M3:M100,$B124)+SUMIFS(Oct2026!K3:K100,Oct2026!L3:L100,$A124,Oct2026!M3:M100,$B124)+SUMIFS(Nov2026!K3:K100,Nov2026!L3:L100,$A124,Nov2026!M3:M100,$B124)+SUMIFS(Dec2026!K3:K100,Dec2026!L3:L100,$A124,Dec2026!M3:M100,$B124)
A125: Miscellaneous | B125: Food & Refreshments | C125: =SUMIFS(Jan2026!K3:K100,Jan2026!L3:L100,$A125,Jan2026!M3:M100,$B125)+SUMIFS(Feb2026!K3:K100,Feb2026!L3:L100,$A125,Feb2026!M3:M100,$B125)+SUMIFS(Mar2026!K3:K100,Mar2026!L3:L100,$A125,Mar2026!M3:M100,$B125)+SUMIFS(Apr2026!K3:K100,Apr2026!L3:L100,$A125,Apr2026!M3:M100,$B125)+SUMIFS(May2026!K3:K100,May2026!L3:L100,$A125,May2026!M3:M100,$B125)+SUMIFS(Jun2026!K3:K100,Jun2026!L3:L100,$A125,Jun2026!M3:M100,$B125)+SUMIFS(Jul2026!K3:K100,Jul2026!L3:L100,$A125,Jul2026!M3:M100,$B125)+SUMIFS(Aug2026!K3:K100,Aug2026!L3:L100,$A125,Aug2026!M3:M100,$B125)+SUMIFS(Sep2026!K3:K100,Sep2026!L3:L100,$A125,Sep2026!M3:M100,$B125)+SUMIFS(Oct2026!K3:K100,Oct2026!L3:L100,$A125,Oct2026!M3:M100,$B125)+SUMIFS(Nov2026!K3:K100,Nov2026!L3:L100,$A125,Nov2026!M3:M100,$B125)+SUMIFS(Dec2026!K3:K100,Dec2026!L3:L100,$A125,Dec2026!M3:M100,$B125)
A126: Miscellaneous | B126: Government Fees | C126: =SUMIFS(Jan2026!K3:K100,Jan2026!L3:L100,$A126,Jan2026!M3:M100,$B126)+SUMIFS(Feb2026!K3:K100,Feb2026!L3:L100,$A126,Feb2026!M3:M100,$B126)+SUMIFS(Mar2026!K3:K100,Mar2026!L3:L100,$A126,Mar2026!M3:M100,$B126)+SUMIFS(Apr2026!K3:K100,Apr2026!L3:L100,$A126,Apr2026!M3:M100,$B126)+SUMIFS(May2026!K3:K100,May2026!L3:L100,$A126,May2026!M3:M100,$B126)+SUMIFS(Jun2026!K3:K100,Jun2026!L3:L100,$A126,Jun2026!M3:M100,$B126)+SUMIFS(Jul2026!K3:K100,Jul2026!L3:L100,$A126,Jul2026!M3:M100,$B126)+SUMIFS(Aug2026!K3:K100,Aug2026!L3:L100,$A126,Aug2026!M3:M100,$B126)+SUMIFS(Sep2026!K3:K100,Sep2026!L3:L100,$A126,Sep2026!M3:M100,$B126)+SUMIFS(Oct2026!K3:K100,Oct2026!L3:L100,$A126,Oct2026!M3:M100,$B126)+SUMIFS(Nov2026!K3:K100,Nov2026!L3:L100,$A126,Nov2026!M3:M100,$B126)+SUMIFS(Dec2026!K3:K100,Dec2026!L3:L100,$A126,Dec2026!M3:M100,$B126)
A127: Miscellaneous | B127: Bank Charges | C127: =SUMIFS(Jan2026!K3:K100,Jan2026!L3:L100,$A127,Jan2026!M3:M100,$B127)+SUMIFS(Feb2026!K3:K100,Feb2026!L3:L100,$A127,Feb2026!M3:M100,$B127)+SUMIFS(Mar2026!K3:K100,Mar2026!L3:L100,$A127,Mar2026!M3:M100,$B127)+SUMIFS(Apr2026!K3:K100,Apr2026!L3:L100,$A127,Apr2026!M3:M100,$B127)+SUMIFS(May2026!K3:K100,May2026!L3:L100,$A127,May2026!M3:M100,$B127)+SUMIFS(Jun2026!K3:K100,Jun2026!L3:L100,$A127,Jun2026!M3:M100,$B127)+SUMIFS(Jul2026!K3:K100,Jul2026!L3:L100,$A127,Jul2026!M3:M100,$B127)+SUMIFS(Aug2026!K3:K100,Aug2026!L3:L100,$A127,Aug2026!M3:M100,$B127)+SUMIFS(Sep2026!K3:K100,Sep2026!L3:L100,$A127,Sep2026!M3:M100,$B127)+SUMIFS(Oct2026!K3:K100,Oct2026!L3:L100,$A127,Oct2026!M3:M100,$B127)+SUMIFS(Nov2026!K3:K100,Nov2026!L3:L100,$A127,Nov2026!M3:M100,$B127)+SUMIFS(Dec2026!K3:K100,Dec2026!L3:L100,$A127,Dec2026!M3:M100,$B127)
A128: Miscellaneous | B128: Miscellaneous Expenses | C128: =SUMIFS(Jan2026!K3:K100,Jan2026!L3:L100,$A128,Jan2026!M3:M100,$B128)+SUMIFS(Feb2026!K3:K100,Feb2026!L3:L100,$A128,Feb2026!M3:M100,$B128)+SUMIFS(Mar2026!K3:K100,Mar2026!L3:L100,$A128,Mar2026!M3:M100,$B128)+SUMIFS(Apr2026!K3:K100,Apr2026!L3:L100,$A128,Apr2026!M3:M100,$B128)+SUMIFS(May2026!K3:K100,May2026!L3:L100,$A128,May2026!M3:M100,$B128)+SUMIFS(Jun2026!K3:K100,Jun2026!L3:L100,$A128,Jun2026!M3:M100,$B128)+SUMIFS(Jul2026!K3:K100,Jul2026!L3:L100,$A128,Jul2026!M3:M100,$B128)+SUMIFS(Aug2026!K3:K100,Aug2026!L3:L100,$A128,Aug2026!M3:M100,$B128)+SUMIFS(Sep2026!K3:K100,Sep2026!L3:L100,$A128,Sep2026!M3:M100,$B128)+SUMIFS(Oct2026!K3:K100,Oct2026!L3:L100,$A128,Oct2026!M3:M100,$B128)+SUMIFS(Nov2026!K3:K100,Nov2026!L3:L100,$A128,Nov2026!M3:M100,$B128)+SUMIFS(Dec2026!K3:K100,Dec2026!L3:L100,$A128,Dec2026!M3:M100,$B128)

Sheet Jan2026
A1: Receipts | I1: Payments
A2: SNO | B2: Date | C2: Receipts | D2: Amount | E2: Category | F2: Payment Mode | I2: Date | J2: Payments | K2: Amount | L2: Main Category | M2: Sub-Category | N2: Payment Mode | O2: Comments
A102: Summary
A103: Opening Balance | B103: 0
A104: Total Receipts | B104: =SUM(D3:D100)
A105: Total Payments | B105: =SUM(K3:K100)
A106: Net / Closing Balance | B106: =B103+B104-B105

Sheet Feb2026
A1: Receipts | I1: Payments
A2: SNO | B2: Date | C2: Receipts | D2: Amount | E2: Category | F2: Payment Mode | I2: Date | J2: Payments | K2: Amount | L2: Main Category | M2: Sub-Category | N2: Payment Mode | O2: Comments
A102: Summary
A103: Opening Balance | B103: ='Jan2026'!B106
A104: Total Receipts | B104: =SUM(D3:D100)
A105: Total Payments | B105: =SUM(K3:K100)
A106: Net / Closing Balance | B106: =B103+B104-B105

Sheet Mar2026
A1: Receipts | I1: Payments
A2: SNO | B2: Date | C2: Receipts | D2: Amount | E2: Category | F2: Payment Mode | I2: Date | J2: Payments | K2: Amount | L2: Main Category | M2: Sub-Category | N2: Payment Mode | O2: Comments
A102: Summary
A103: Opening Balance | B103: ='Feb2026'!B106
A104: Total Receipts | B104: =SUM(D3:D100)
A105: Total Payments | B105: =SUM(K3:K100)
A106: Net / Closing Balance | B106: =B103+B104-B105

Sheet Apr2026
A1: Receipts | I1: Payments
A2: SNO | B2: Date | C2: Receipts | D2: Amount | E2: Category | F2: Payment Mode | I2: Date | J2: Payments | K2: Amount | L2: Main Category | M2: Sub-Category | N2: Payment Mode | O2: Comments
A102: Summary
A103: Opening Balance | B103: ='Mar2026'!B106
A104: Total Receipts | B104: =SUM(D3:D100)
A105: Total Payments | B105: =SUM(K3:K100)
A106: Net / Closing Balance | B106: =B103+B104-B105

Sheet May2026
A1: Receipts | I1: Payments
A2: SNO | B2: Date | C2: Receipts | D2: Amount | E2: Category | F2: Payment Mode | I2: Date | J2: Payments | K2: Amount | L2: Main Category | M2: Sub-Category | N2: Payment Mode | O2: Comments
A102: Summary
A103: Opening Balance | B103: ='Apr2026'!B106
A104: Total Receipts | B104: =SUM(D3:D100)
A105: Total Payments | B105: =SUM(K3:K100)
A106: Net / Closing Balance | B106: =B103+B104-B105

Sheet Jun2026
A1: Receipts | I1: Payments
A2: SNO | B2: Date | C2: Receipts | D2: Amount | E2: Category | F2: Payment Mode | I2: Date | J2: Payments | K2: Amount | L2: Main Category | M2: Sub-Category | N2: Payment Mode | O2: Comments
A102: Summary
A103: Opening Balance | B103: ='May2026'!B106
A104: Total Receipts | B104: =SUM(D3:D100)
A105: Total Payments | B105: =SUM(K3:K100)
A106: Net / Closing Balance | B106: =B103+B104-B105

Sheet Jul2026
A1: Receipts | I1: Payments
A2: SNO | B2: Date | C2: Receipts | D2: Amount | E2: Category | F2: Payment Mode | I2: Date | J2: Payments | K2: Amount | L2: Main Category | M2: Sub-Category | N2: Payment Mode | O2: Comments
A102: Summary
A103: Opening Balance | B103: ='Jun2026'!B106
A104: Total Receipts | B104: =SUM(D3:D100)
A105: Total Payments | B105: =SUM(K3:K100)
A106: Net / Closing Balance | B106: =B103+B104-B105

Sheet Aug2026
A1: Receipts | I1: Payments
A2: SNO | B2: Date | C2: Receipts | D2: Amount | E2: Category | F2: Payment Mode | I2: Date | J2: Payments | K2: Amount | L2: Main Category | M2: Sub-Category | N2: Payment Mode | O2: Comments
A102: Summary
A103: Opening Balance | B103: ='Jul2026'!B106
A104: Total Receipts | B104: =SUM(D3:D100)
A105: Total Payments | B105: =SUM(K3:K100)
A106: Net / Closing Balance | B106: =B103+B104-B105

Sheet Sep2026
A1: Receipts | I1: Payments
A2: SNO | B2: Date | C2: Receipts | D2: Amount | E2: Category | F2: Payment Mode | I2: Date | J2: Payments | K2: Amount | L2: Main Category | M2: Sub-Category | N2: Payment Mode | O2: Comments
A102: Summary
A103: Opening Balance | B103: ='Aug2026'!B106
A104: Total Receipts | B104: =SUM(D3:D100)
A105: Total Payments | B105: =SUM(K3:K100)
A106: Net / Closing Balance | B106: =B103+B104-B105

Sheet Oct2026
A1: Receipts | I1: Payments
A2: SNO | B2: Date | C2: Receipts | D2: Amount | E2: Category | F2: Payment Mode | I2: Date | J2: Payments | K2: Amount | L2: Main Category | M2: Sub-Category | N2: Payment Mode | O2: Comments
A102: Summary
A103: Opening Balance | B103: ='Sep2026'!B106
A104: Total Receipts | B104: =SUM(D3:D100)
A105: Total Payments | B105: =SUM(K3:K100)
A106: Net / Closing Balance | B106: =B103+B104-B105

Sheet Nov2026
A1: Receipts | I1: Payments
A2: SNO | B2: Date | C2: Receipts | D2: Amount | E2: Category | F2: Payment Mode | I2: Date | J2: Payments | K2: Amount | L2: Main Category | M2: Sub-Category | N2: Payment Mode | O2: Comments
A102: Summary
A103: Opening Balance | B103: ='Oct2026'!B106
A104: Total Receipts | B104: =SUM(D3:D100)
A105: Total Payments | B105: =SUM(K3:K100)
A106: Net / Closing Balance | B106: =B103+B104-B105

Sheet Dec2026
A1: Receipts | I1: Payments
A2: SNO | B2: Date | C2: Receipts | D2: Amount | E2: Category | F2: Payment Mode | I2: Date | J2: Payments | K2: Amount | L2: Main Category | M2: Sub-Category | N2: Payment Mode | O2: Comments
A102: Summary
A103: Opening Balance | B103: ='Nov2026'!B106
A104: Total Receipts | B104: =SUM(D3:D100)
A105: Total Payments | B105: =SUM(K3:K100)
A106: Net / Closing Balance | B106: =B103+B104-B105

Sheet Categories
A1: Income Categories | C1: Main Category / Sub-category Reference | F1: Unique Main Categories | H1: Sub-categories by Main Category
A2: Income Categories | C2: Main Category | D2: Sub-category | F2: Unique Main Categories | H2: Land & Legal | I2: Site Development | J2: Utilities | K2: Landscaping | L2: Buildings & Amenities | M2: Labour & Contractors | N2: Materials | O2: Operations | P2: Marketing & Sales | Q2: Miscellaneous
A3: Investor Capital | C3: Land & Legal | D3: Land Purchase | F3: Land & Legal | H3: Land Purchase | I3: Land Clearing | J3: Borewell | K3: Plantation | L3: Security Room | M3: Labour Wages | N3: Cement | O3: Security | P3: Advertisement | Q3: Travel Expenses
A4: Partner Contribution | C4: Land & Legal | D4: Advance Payments | F4: Site Development | H4: Advance Payments | I4: Earthwork & Levelling | J4: Water Pipelines | K4: Miyawaki Forest | L4: Site Office | M4: Contractor Payments | N4: Sand | O4: Housekeeping | P4: Flex Boards | Q4: Food & Refreshments
A5: Loan Received | C5: Land & Legal | D5: Registration Charges | F5: Utilities | H5: Registration Charges | I5: Road Formation | J5: Water Tank | K5: Lawn Development | L5: Clubhouse | M5: Machinery Hire | N5: Metal | O5: Fuel & Diesel | P5: Brochures | Q5: Government Fees
A6: Sales | C6: Land & Legal | D6: Stamp Duty | F6: Landscaping | H6: Stamp Duty | I6: Blacktop Roads | J6: Electricity Connection | K6: Irrigation/Drip System | L6: Swimming Pool | M6: Excavator/JCB | N6: Bricks | O6: Vehicle Expenses | P6: Events | Q6: Bank Charges
C7: Land & Legal | D7: Legal Fees | F7: Buildings & Amenities | H7: Legal Fees | I7: Interlocking Pavers | J7: Transformer | K7: Garden Maintenance | L7: Gazebo | M7: Tractor & Transport | N7: Steel | O7: Repairs & Maintenance | P7: Photography & Drone | Q7: Miscellaneous Expenses
C8: Land & Legal | D8: Survey Charges | F8: Labour & Contractors | H8: Survey Charges | I8: Compound Wall | J8: Street Lights | L8: Children's Play Area | N8: Pipes | O8: Office Expenses | P8: Digital Marketing
C9: Land & Legal | D9: Documentation | F9: Materials | H9: Documentation | I9: Entrance Gate | J9: Generator | L9: Sports Courts | N9: Electrical Materials | O9: Internet & Phone
C10: Site Development | D10: Land Clearing | F10: Operations | I10: Drainage | L10: Toilets | N10: Paint
C11: Site Development | D11: Earthwork & Levelling | F11: Marketing & Sales | I11: Culverts | N11: Tiles
C12: Site Development | D12: Road Formation | F12: Miscellaneous
C13: Site Development | D13: Blacktop Roads
C14: Site Development | D14: Interlocking Pavers
C15: Site Development | D15: Compound Wall
C16: Site Development | D16: Entrance Gate
C17: Site Development | D17: Drainage
C18: Site Development | D18: Culverts
C19: Utilities | D19: Borewell
C20: Utilities | D20: Water Pipelines
C21: Utilities | D21: Water Tank
C22: Utilities | D22: Electricity Connection
C23: Utilities | D23: Transformer
C24: Utilities | D24: Street Lights
... C70: Miscellaneous | D70: Miscellaneous Expenses
